{"status":200,"currentLocale":"en","ranges":{"11001001-11001999":{"citation":"1 Kings&nbsp;1:1-53","link":"https:\/\/www.jw.org\/en\/publications\/bible\/nwt\/books\/1-kings\/1\/#v11001001-v11001053","validRange":"11001001-11001053","html":"<span class=\"verse\" id=\"v11001001\"><span class=\"style-b\"><span class=\"chapterNum\"><a href='\/en\/publications\/bible\/nwt\/books\/json\/html\/11001001-11001999#v11001001' data-anchor='#v11001001'>1 <\/a><\/span>\u00a0Now King David was old,<a class=\"xrefLink jsBibleLink\" id=\"xreflink16321930\" href=\"\/en\/publications\/bible\/nwt\/books\/mcr\/16321930\/\" data-bible=\"nwt\" data-targetverses=\"10005004,13029026-13029027\">+<\/a> advanced in years,<a class=\"footnoteLink\" id=\"footnotesource16321954\" href='\/en\/publications\/bible\/nwt\/books\/json\/html\/11001001-11001999#fn16321954' data-anchor='#fn16321954'>*<\/a> and although they would cover him with garments, he could not get warm.<\/span><\/span>\n\n<span class=\"verse\" id=\"v11001002\"><span class=\"style-b\"><sup class=\"verseNum\"><a href='\/en\/publications\/bible\/nwt\/books\/json\/html\/11001001-11001999#v11001002' data-anchor='#v11001002'>2\u00a0<\/a><\/sup>\u00a0So his servants said to him: \u201cLet a girl, a virgin, be found for my lord the king, and she will wait on the king as his nurse. She will lie in your arms so that my lord the king may feel warm.\u201d<\/span><\/span>\n\n<span class=\"verse\" id=\"v11001003\"><span class=\"style-b\"><sup class=\"verseNum\"><a href='\/en\/publications\/bible\/nwt\/books\/json\/html\/11001001-11001999#v11001003' data-anchor='#v11001003'>3\u00a0<\/a><\/sup>\u00a0They searched throughout all the territory of Israel for a beautiful girl, and they found Ab\u02b9i\u00b7shag<a class=\"xrefLink jsBibleLink\" id=\"xreflink16321988\" href=\"\/en\/publications\/bible\/nwt\/books\/mcr\/16321988\/\" data-bible=\"nwt\" data-targetverses=\"11002017,11002022\">+<\/a> the Shu\u02b9nam\u00b7mite<a class=\"xrefLink jsBibleLink\" id=\"xreflink16322005\" href=\"\/en\/publications\/bible\/nwt\/books\/mcr\/16322005\/\" data-bible=\"nwt\" data-targetverses=\"6019017-6019018\">+<\/a> and brought her in to the king.<\/span><\/span>\n\n<span class=\"verse\" id=\"v11001004\"><span class=\"style-b\"><sup class=\"verseNum\"><a href='\/en\/publications\/bible\/nwt\/books\/json\/html\/11001001-11001999#v11001004' data-anchor='#v11001004'>4\u00a0<\/a><\/sup>\u00a0The girl was extremely beautiful, and she became the king\u2019s nurse and waited on him, but the king did not have sexual relations with her.<\/span>\n<span class=\"parabreak\"><\/span><\/span>\n\n<span class=\"verse\" id=\"v11001005\"><span class=\"style-b first\"><sup class=\"verseNum\"><a href='\/en\/publications\/bible\/nwt\/books\/json\/html\/11001001-11001999#v11001005' data-anchor='#v11001005'>5\u00a0<\/a><\/sup>\u00a0Meanwhile, Ad\u00b7o\u00b7ni\u02b9jah<a class=\"xrefLink jsBibleLink\" id=\"xreflink16322046\" href=\"\/en\/publications\/bible\/nwt\/books\/mcr\/16322046\/\" data-bible=\"nwt\" data-targetverses=\"10003002,10003004,13003001-13003002\">+<\/a> the son of Hag\u02b9gith was exalting himself, saying: \u201cI am going to be king!\u201d He had a chariot made for himself with horsemen and 50 men to run before him.<a class=\"xrefLink jsBibleLink\" id=\"xreflink16322062\" href=\"\/en\/publications\/bible\/nwt\/books\/mcr\/16322062\/\" data-bible=\"nwt\" data-targetverses=\"10015001\">+<\/a><\/span><\/span>\n\n<span class=\"verse\" id=\"v11001006\"><span class=\"style-b\"><sup class=\"verseNum\"><a href='\/en\/publications\/bible\/nwt\/books\/json\/html\/11001001-11001999#v11001006' data-anchor='#v11001006'>6\u00a0<\/a><\/sup>\u00a0But his father had never confronted him<a class=\"footnoteLink\" id=\"footnotesource16322093\" href='\/en\/publications\/bible\/nwt\/books\/json\/html\/11001001-11001999#fn16322093' data-anchor='#fn16322093'>*<\/a> by saying: \u201cWhy have you done this?\u201d He was also very handsome, and his mother had given birth to him after Ab\u02b9sa\u00b7lom.<\/span><\/span>\n\n<span class=\"verse\" id=\"v11001007\"><span class=\"style-b\"><sup class=\"verseNum\"><a href='\/en\/publications\/bible\/nwt\/books\/json\/html\/11001001-11001999#v11001007' data-anchor='#v11001007'>7\u00a0<\/a><\/sup>\u00a0He conferred with Jo\u02b9ab the son of Ze\u00b7ru\u02b9iah and A\u00b7bi\u02b9a\u00b7thar<a class=\"xrefLink jsBibleLink\" id=\"xreflink16322120\" href=\"\/en\/publications\/bible\/nwt\/books\/mcr\/16322120\/\" data-bible=\"nwt\" data-targetverses=\"10020025\">+<\/a> the priest, and they offered Ad\u00b7o\u00b7ni\u02b9jah help and support.<a class=\"xrefLink jsBibleLink\" id=\"xreflink16322133\" href=\"\/en\/publications\/bible\/nwt\/books\/mcr\/16322133\/\" data-bible=\"nwt\" data-targetverses=\"11002022\">+<\/a><\/span><\/span>\n\n<span class=\"verse\" id=\"v11001008\"><span class=\"style-b\"><sup class=\"verseNum\"><a href='\/en\/publications\/bible\/nwt\/books\/json\/html\/11001001-11001999#v11001008' data-anchor='#v11001008'>8\u00a0<\/a><\/sup>\u00a0But Za\u02b9dok<a class=\"xrefLink jsBibleLink\" id=\"xreflink16322163\" href=\"\/en\/publications\/bible\/nwt\/books\/mcr\/16322163\/\" data-bible=\"nwt\" data-targetverses=\"10008017\">+<\/a> the priest, Be\u00b7nai\u02b9ah<a class=\"xrefLink jsBibleLink\" id=\"xreflink16322173\" href=\"\/en\/publications\/bible\/nwt\/books\/mcr\/16322173\/\" data-bible=\"nwt\" data-targetverses=\"10020023,13027005\">+<\/a> the son of Je\u00b7hoi\u02b9a\u00b7da, Nathan<a class=\"xrefLink jsBibleLink\" id=\"xreflink16322192\" href=\"\/en\/publications\/bible\/nwt\/books\/mcr\/16322192\/\" data-bible=\"nwt\" data-targetverses=\"10007002,10012001\">+<\/a> the prophet, Shim\u02b9e\u00b7i,<a class=\"xrefLink jsBibleLink\" id=\"xreflink16322209\" href=\"\/en\/publications\/bible\/nwt\/books\/mcr\/16322209\/\" data-bible=\"nwt\" data-targetverses=\"11004007,11004018\">+<\/a> Re\u02b9i, and David\u2019s mighty warriors<a class=\"xrefLink jsBibleLink\" id=\"xreflink16322225\" href=\"\/en\/publications\/bible\/nwt\/books\/mcr\/16322225\/\" data-bible=\"nwt\" data-targetverses=\"10023008,13011010\">+<\/a> did not support Ad\u00b7o\u00b7ni\u02b9jah.<\/span>\n<span class=\"parabreak\"><\/span><\/span>\n\n<span class=\"verse\" id=\"v11001009\"><span class=\"style-b first\"><sup class=\"verseNum\"><a href='\/en\/publications\/bible\/nwt\/books\/json\/html\/11001001-11001999#v11001009' data-anchor='#v11001009'>9\u00a0<\/a><\/sup>\u00a0Eventually Ad\u00b7o\u00b7ni\u02b9jah held a sacrifice<a class=\"xrefLink jsBibleLink\" id=\"xreflink16322246\" href=\"\/en\/publications\/bible\/nwt\/books\/mcr\/16322246\/\" data-bible=\"nwt\" data-targetverses=\"10015012\">+<\/a> of sheep, cattle, and fattened animals by the stone of Zo\u02b9he\u00b7leth, which is near En-ro\u02b9gel, and he invited all his brothers the king\u2019s sons, and all the men of Judah the king\u2019s servants.<\/span><\/span>\n\n<span class=\"verse\" id=\"v11001010\"><span class=\"style-b\"><sup class=\"verseNum\"><a href='\/en\/publications\/bible\/nwt\/books\/json\/html\/11001001-11001999#v11001010' data-anchor='#v11001010'>10\u00a0<\/a><\/sup>\u00a0But he did not invite Nathan the prophet, Be\u00b7nai\u02b9ah and the mighty warriors, or Sol\u02b9o\u00b7mon his brother.<\/span><\/span>\n\n<span class=\"verse\" id=\"v11001011\"><span class=\"style-b\"><sup class=\"verseNum\"><a href='\/en\/publications\/bible\/nwt\/books\/json\/html\/11001001-11001999#v11001011' data-anchor='#v11001011'>11\u00a0<\/a><\/sup>\u00a0Nathan<a class=\"xrefLink jsBibleLink\" id=\"xreflink16322284\" href=\"\/en\/publications\/bible\/nwt\/books\/mcr\/16322284\/\" data-bible=\"nwt\" data-targetverses=\"10007004-10007005\">+<\/a> then said to Bath-she\u02b9ba,<a class=\"xrefLink jsBibleLink\" id=\"xreflink16322297\" href=\"\/en\/publications\/bible\/nwt\/books\/mcr\/16322297\/\" data-bible=\"nwt\" data-targetverses=\"10011003,10011027\">+<\/a> Sol\u02b9o\u00b7mon\u2019s mother:<a class=\"xrefLink jsBibleLink\" id=\"xreflink16322309\" href=\"\/en\/publications\/bible\/nwt\/books\/mcr\/16322309\/\" data-bible=\"nwt\" data-targetverses=\"10012024\">+<\/a> \u201cHave you not heard that Ad\u00b7o\u00b7ni\u02b9jah<a class=\"xrefLink jsBibleLink\" id=\"xreflink16322326\" href=\"\/en\/publications\/bible\/nwt\/books\/mcr\/16322326\/\" data-bible=\"nwt\" data-targetverses=\"10003002,10003004\">+<\/a> the son of Hag\u02b9gith has become king, and our lord David does not know anything about it?<\/span><\/span>\n\n<span class=\"verse\" id=\"v11001012\"><span class=\"style-b\"><sup class=\"verseNum\"><a href='\/en\/publications\/bible\/nwt\/books\/json\/html\/11001001-11001999#v11001012' data-anchor='#v11001012'>12\u00a0<\/a><\/sup>\u00a0So now come, please, and let me advise you, so that you may save your own life and the life of<a class=\"footnoteLink\" id=\"footnotesource16322380\" href='\/en\/publications\/bible\/nwt\/books\/json\/html\/11001001-11001999#fn16322380' data-anchor='#fn16322380'>*<\/a> your son Sol\u02b9o\u00b7mon.<a class=\"xrefLink jsBibleLink\" id=\"xreflink16322359\" href=\"\/en\/publications\/bible\/nwt\/books\/mcr\/16322359\/\" data-bible=\"nwt\" data-targetverses=\"7009004-7009006,11001021,12011001\">+<\/a><\/span><\/span>\n\n<span class=\"verse\" id=\"v11001013\"><span class=\"style-b\"><sup class=\"verseNum\"><a href='\/en\/publications\/bible\/nwt\/books\/json\/html\/11001001-11001999#v11001013' data-anchor='#v11001013'>13\u00a0<\/a><\/sup>\u00a0Go in to King David and say to him, \u2018Was it not you, my lord the king, who swore to your servant, saying: \u201cYour son Sol\u02b9o\u00b7mon will become king after me, and he is the one who will sit on my throne\u201d?<a class=\"xrefLink jsBibleLink\" id=\"xreflink16322405\" href=\"\/en\/publications\/bible\/nwt\/books\/mcr\/16322405\/\" data-bible=\"nwt\" data-targetverses=\"13022009,13028005,13029001\">+<\/a> So why has Ad\u00b7o\u00b7ni\u02b9jah become king?\u2019<\/span><\/span>\n\n<span class=\"verse\" id=\"v11001014\"><span class=\"style-b\"><sup class=\"verseNum\"><a href='\/en\/publications\/bible\/nwt\/books\/json\/html\/11001001-11001999#v11001014' data-anchor='#v11001014'>14\u00a0<\/a><\/sup>\u00a0While you are still there speaking with the king, I will come in after you and confirm your words.\u201d<\/span>\n<span class=\"parabreak\"><\/span><\/span>\n\n<span class=\"verse\" id=\"v11001015\"><span class=\"style-b first\"><sup class=\"verseNum\"><a href='\/en\/publications\/bible\/nwt\/books\/json\/html\/11001001-11001999#v11001015' data-anchor='#v11001015'>15\u00a0<\/a><\/sup>\u00a0So Bath-she\u02b9ba went in to the king, into his private room. The king was very old, and Ab\u02b9i\u00b7shag<a class=\"xrefLink jsBibleLink\" id=\"xreflink16322455\" href=\"\/en\/publications\/bible\/nwt\/books\/mcr\/16322455\/\" data-bible=\"nwt\" data-targetverses=\"11001001,11001003\">+<\/a> the Shu\u02b9nam\u00b7mite was waiting on the king.<\/span><\/span>\n\n<span class=\"verse\" id=\"v11001016\"><span class=\"style-b\"><sup class=\"verseNum\"><a href='\/en\/publications\/bible\/nwt\/books\/json\/html\/11001001-11001999#v11001016' data-anchor='#v11001016'>16\u00a0<\/a><\/sup>\u00a0Then Bath-she\u02b9ba bowed low and prostrated herself to the king, and the king said: \u201cWhat is your request?\u201d<\/span><\/span>\n\n<span class=\"verse\" id=\"v11001017\"><span class=\"style-b\"><sup class=\"verseNum\"><a href='\/en\/publications\/bible\/nwt\/books\/json\/html\/11001001-11001999#v11001017' data-anchor='#v11001017'>17\u00a0<\/a><\/sup>\u00a0She replied: \u201cMy lord, it was you who swore by Jehovah your God to your servant, \u2018Your son Sol\u02b9o\u00b7mon will become king after me, and he is the one who will sit on my throne.\u2019<a class=\"xrefLink jsBibleLink\" id=\"xreflink16322504\" href=\"\/en\/publications\/bible\/nwt\/books\/mcr\/16322504\/\" data-bible=\"nwt\" data-targetverses=\"11001013,13022009-13022010\">+<\/a><\/span><\/span>\n\n<span class=\"verse\" id=\"v11001018\"><span class=\"style-b\"><sup class=\"verseNum\"><a href='\/en\/publications\/bible\/nwt\/books\/json\/html\/11001001-11001999#v11001018' data-anchor='#v11001018'>18\u00a0<\/a><\/sup>\u00a0But look! Ad\u00b7o\u00b7ni\u02b9jah has become king, and my lord the king does not know anything about it.<a class=\"xrefLink jsBibleLink\" id=\"xreflink16322532\" href=\"\/en\/publications\/bible\/nwt\/books\/mcr\/16322532\/\" data-bible=\"nwt\" data-targetverses=\"11001005,11001011\">+<\/a><\/span><\/span>\n\n<span class=\"verse\" id=\"v11001019\"><span class=\"style-b\"><sup class=\"verseNum\"><a href='\/en\/publications\/bible\/nwt\/books\/json\/html\/11001001-11001999#v11001019' data-anchor='#v11001019'>19\u00a0<\/a><\/sup>\u00a0He sacrificed bulls, fattened animals, and sheep in great quantity and invited all the sons of the king and A\u00b7bi\u02b9a\u00b7thar the priest and Jo\u02b9ab the chief of the army;<a class=\"xrefLink jsBibleLink\" id=\"xreflink16322567\" href=\"\/en\/publications\/bible\/nwt\/books\/mcr\/16322567\/\" data-bible=\"nwt\" data-targetverses=\"11001007\">+<\/a> but he did not invite your servant Sol\u02b9o\u00b7mon.<a class=\"xrefLink jsBibleLink\" id=\"xreflink16322579\" href=\"\/en\/publications\/bible\/nwt\/books\/mcr\/16322579\/\" data-bible=\"nwt\" data-targetverses=\"11001009-11001010\">+<\/a><\/span><\/span>\n\n<span class=\"verse\" id=\"v11001020\"><span class=\"style-b\"><sup class=\"verseNum\"><a href='\/en\/publications\/bible\/nwt\/books\/json\/html\/11001001-11001999#v11001020' data-anchor='#v11001020'>20\u00a0<\/a><\/sup>\u00a0And now, my lord the king, the eyes of all Israel are upon you to tell them who will sit on the throne of my lord the king after him.<\/span><\/span>\n\n<span class=\"verse\" id=\"v11001021\"><span class=\"style-b\"><sup class=\"verseNum\"><a href='\/en\/publications\/bible\/nwt\/books\/json\/html\/11001001-11001999#v11001021' data-anchor='#v11001021'>21\u00a0<\/a><\/sup>\u00a0Otherwise, as soon as my lord the king is laid to rest with his forefathers, I and also my son Sol\u02b9o\u00b7mon will be considered traitors.\u201d<\/span>\n<span class=\"parabreak\"><\/span><\/span>\n\n<span class=\"verse\" id=\"v11001022\"><span class=\"style-b first\"><sup class=\"verseNum\"><a href='\/en\/publications\/bible\/nwt\/books\/json\/html\/11001001-11001999#v11001022' data-anchor='#v11001022'>22\u00a0<\/a><\/sup>\u00a0And while she was still speaking to the king, Nathan the prophet came in.<a class=\"xrefLink jsBibleLink\" id=\"xreflink16322634\" href=\"\/en\/publications\/bible\/nwt\/books\/mcr\/16322634\/\" data-bible=\"nwt\" data-targetverses=\"11001014\">+<\/a><\/span><\/span>\n\n<span class=\"verse\" id=\"v11001023\"><span class=\"style-b\"><sup class=\"verseNum\"><a href='\/en\/publications\/bible\/nwt\/books\/json\/html\/11001001-11001999#v11001023' data-anchor='#v11001023'>23\u00a0<\/a><\/sup>\u00a0At once the king was told: \u201cHere is Nathan the prophet!\u201d He came in before the king and prostrated himself to the king with his face to the ground.<\/span><\/span>\n\n<span class=\"verse\" id=\"v11001024\"><span class=\"style-b\"><sup class=\"verseNum\"><a href='\/en\/publications\/bible\/nwt\/books\/json\/html\/11001001-11001999#v11001024' data-anchor='#v11001024'>24\u00a0<\/a><\/sup>\u00a0Then Nathan said: \u201cMy lord the king, did you say, \u2018Ad\u00b7o\u00b7ni\u02b9jah will become king after me, and he is the one who will sit on my throne\u2019?<a class=\"xrefLink jsBibleLink\" id=\"xreflink16322679\" href=\"\/en\/publications\/bible\/nwt\/books\/mcr\/16322679\/\" data-bible=\"nwt\" data-targetverses=\"11001005\">+<\/a><\/span><\/span>\n\n<span class=\"verse\" id=\"v11001025\"><span class=\"style-b\"><sup class=\"verseNum\"><a href='\/en\/publications\/bible\/nwt\/books\/json\/html\/11001001-11001999#v11001025' data-anchor='#v11001025'>25\u00a0<\/a><\/sup>\u00a0For today he has gone down to sacrifice<a class=\"xrefLink jsBibleLink\" id=\"xreflink16322708\" href=\"\/en\/publications\/bible\/nwt\/books\/mcr\/16322708\/\" data-bible=\"nwt\" data-targetverses=\"10015012\">+<\/a> bulls, fattened animals, and sheep in great quantity, and he has invited all the sons of the king and the chiefs of the army and A\u00b7bi\u02b9a\u00b7thar the priest.<a class=\"xrefLink jsBibleLink\" id=\"xreflink16322722\" href=\"\/en\/publications\/bible\/nwt\/books\/mcr\/16322722\/\" data-bible=\"nwt\" data-targetverses=\"11001005,11001007\">+<\/a> They are there eating and drinking with him, and they keep saying, \u2018Long live King Ad\u00b7o\u00b7ni\u02b9jah!\u2019<\/span><\/span>\n\n<span class=\"verse\" id=\"v11001026\"><span class=\"style-b\"><sup class=\"verseNum\"><a href='\/en\/publications\/bible\/nwt\/books\/json\/html\/11001001-11001999#v11001026' data-anchor='#v11001026'>26\u00a0<\/a><\/sup>\u00a0But he did not invite me, your servant, or Za\u02b9dok the priest, or Be\u00b7nai\u02b9ah<a class=\"xrefLink jsBibleLink\" id=\"xreflink16322759\" href=\"\/en\/publications\/bible\/nwt\/books\/mcr\/16322759\/\" data-bible=\"nwt\" data-targetverses=\"13027005\">+<\/a> the son of Je\u00b7hoi\u02b9a\u00b7da, or your servant Sol\u02b9o\u00b7mon.<\/span><\/span>\n\n<span class=\"verse\" id=\"v11001027\"><span class=\"style-b\"><sup class=\"verseNum\"><a href='\/en\/publications\/bible\/nwt\/books\/json\/html\/11001001-11001999#v11001027' data-anchor='#v11001027'>27\u00a0<\/a><\/sup>\u00a0Has my lord the king authorized this without telling your servant who should sit on the throne of my lord the king after him?\u201d<\/span>\n<span class=\"parabreak\"><\/span><\/span>\n\n<span class=\"verse\" id=\"v11001028\"><span class=\"style-b first\"><sup class=\"verseNum\"><a href='\/en\/publications\/bible\/nwt\/books\/json\/html\/11001001-11001999#v11001028' data-anchor='#v11001028'>28\u00a0<\/a><\/sup>\u00a0King David now answered: \u201cCall Bath-she\u02b9ba for me.\u201d At that she came in and stood before the king.<\/span><\/span>\n\n<span class=\"verse\" id=\"v11001029\"><span class=\"style-b\"><sup class=\"verseNum\"><a href='\/en\/publications\/bible\/nwt\/books\/json\/html\/11001001-11001999#v11001029' data-anchor='#v11001029'>29\u00a0<\/a><\/sup>\u00a0The king then swore an oath: \u201cAs surely as Jehovah is living, the one who rescued me<a class=\"footnoteLink\" id=\"footnotesource16322843\" href='\/en\/publications\/bible\/nwt\/books\/json\/html\/11001001-11001999#fn16322843' data-anchor='#fn16322843'>*<\/a> out of all distress,<a class=\"xrefLink jsBibleLink\" id=\"xreflink16322822\" href=\"\/en\/publications\/bible\/nwt\/books\/mcr\/16322822\/\" data-bible=\"nwt\" data-targetverses=\"19071023,19103004\">+<\/a><\/span><\/span>\n\n<span class=\"verse\" id=\"v11001030\"><span class=\"style-b\"><sup class=\"verseNum\"><a href='\/en\/publications\/bible\/nwt\/books\/json\/html\/11001001-11001999#v11001030' data-anchor='#v11001030'>30\u00a0<\/a><\/sup>\u00a0just as I swore to you by Jehovah the God of Israel, saying, \u2018Your son Sol\u02b9o\u00b7mon will become king after me, and he is the one who will sit on my throne in my place!\u2019 that is what I will bring about this day.\u201d<\/span><\/span>\n\n<span class=\"verse\" id=\"v11001031\"><span class=\"style-b\"><sup class=\"verseNum\"><a href='\/en\/publications\/bible\/nwt\/books\/json\/html\/11001001-11001999#v11001031' data-anchor='#v11001031'>31\u00a0<\/a><\/sup>\u00a0Then Bath-she\u02b9ba bowed low with her face to the ground and prostrated herself to the king and said: \u201cMay my lord King David live forever!\u201d<\/span>\n<span class=\"parabreak\"><\/span><\/span>\n\n<span class=\"verse\" id=\"v11001032\"><span class=\"style-b first\"><sup class=\"verseNum\"><a href='\/en\/publications\/bible\/nwt\/books\/json\/html\/11001001-11001999#v11001032' data-anchor='#v11001032'>32\u00a0<\/a><\/sup>\u00a0Immediately King David said: \u201cCall for me Za\u02b9dok the priest, Nathan the prophet, and Be\u00b7nai\u02b9ah<a class=\"xrefLink jsBibleLink\" id=\"xreflink16322898\" href=\"\/en\/publications\/bible\/nwt\/books\/mcr\/16322898\/\" data-bible=\"nwt\" data-targetverses=\"10020023,10023020,13027005\">+<\/a> the son of Je\u00b7hoi\u02b9a\u00b7da.\u201d<a class=\"xrefLink jsBibleLink\" id=\"xreflink16322918\" href=\"\/en\/publications\/bible\/nwt\/books\/mcr\/16322918\/\" data-bible=\"nwt\" data-targetverses=\"11001008\">+<\/a> So they came in before the king.<\/span><\/span>\n\n<span class=\"verse\" id=\"v11001033\"><span class=\"style-b\"><sup class=\"verseNum\"><a href='\/en\/publications\/bible\/nwt\/books\/json\/html\/11001001-11001999#v11001033' data-anchor='#v11001033'>33\u00a0<\/a><\/sup>\u00a0The king said to them: \u201cTake with you the servants of your lord, and have my son Sol\u02b9o\u00b7mon ride on my own mule,<a class=\"footnoteLink\" id=\"footnotesource16322977\" href='\/en\/publications\/bible\/nwt\/books\/json\/html\/11001001-11001999#fn16322977' data-anchor='#fn16322977'>*<\/a><a class=\"xrefLink jsBibleLink\" id=\"xreflink16322948\" href=\"\/en\/publications\/bible\/nwt\/books\/mcr\/16322948\/\" data-bible=\"nwt\" data-targetverses=\"11001038,42019033-42019035\">+<\/a> and lead him down to Gi\u02b9hon.<a class=\"xrefLink jsBibleLink\" id=\"xreflink16322958\" href=\"\/en\/publications\/bible\/nwt\/books\/mcr\/16322958\/\" data-bible=\"nwt\" data-targetverses=\"14032030\">+<\/a><\/span><\/span>\n\n<span class=\"verse\" id=\"v11001034\"><span class=\"style-b\"><sup class=\"verseNum\"><a href='\/en\/publications\/bible\/nwt\/books\/json\/html\/11001001-11001999#v11001034' data-anchor='#v11001034'>34\u00a0<\/a><\/sup>\u00a0Za\u02b9dok the priest and Nathan the prophet will anoint him<a class=\"xrefLink jsBibleLink\" id=\"xreflink16322995\" href=\"\/en\/publications\/bible\/nwt\/books\/mcr\/16322995\/\" data-bible=\"nwt\" data-targetverses=\"9016013\">+<\/a> there as king over Israel; then blow the horn and say, \u2018Long live King Sol\u02b9o\u00b7mon!\u2019<a class=\"xrefLink jsBibleLink\" id=\"xreflink16323014\" href=\"\/en\/publications\/bible\/nwt\/books\/mcr\/16323014\/\" data-bible=\"nwt\" data-targetverses=\"9010001,9010024,10015010,12011012\">+<\/a><\/span><\/span>\n\n<span class=\"verse\" id=\"v11001035\"><span class=\"style-b\"><sup class=\"verseNum\"><a href='\/en\/publications\/bible\/nwt\/books\/json\/html\/11001001-11001999#v11001035' data-anchor='#v11001035'>35\u00a0<\/a><\/sup>\u00a0Then follow him back, and he will come in and sit on my throne; and he will be king in my place, and I will commission him as leader over Israel and over Judah.\u201d<\/span><\/span>\n\n<span class=\"verse\" id=\"v11001036\"><span class=\"style-b\"><sup class=\"verseNum\"><a href='\/en\/publications\/bible\/nwt\/books\/json\/html\/11001001-11001999#v11001036' data-anchor='#v11001036'>36\u00a0<\/a><\/sup>\u00a0At once Be\u00b7nai\u02b9ah the son of Je\u00b7hoi\u02b9a\u00b7da said to the king: \u201cAmen! May Jehovah the God of my lord the king confirm it.<\/span><\/span>\n\n<span class=\"verse\" id=\"v11001037\"><span class=\"style-b\"><sup class=\"verseNum\"><a href='\/en\/publications\/bible\/nwt\/books\/json\/html\/11001001-11001999#v11001037' data-anchor='#v11001037'>37\u00a0<\/a><\/sup>\u00a0Just as Jehovah was with my lord the king, so let him be with Sol\u02b9o\u00b7mon,<a class=\"xrefLink jsBibleLink\" id=\"xreflink16323079\" href=\"\/en\/publications\/bible\/nwt\/books\/mcr\/16323079\/\" data-bible=\"nwt\" data-targetverses=\"13028020\">+<\/a> and may He make his throne greater than the throne of my lord King David.\u201d<a class=\"xrefLink jsBibleLink\" id=\"xreflink16323101\" href=\"\/en\/publications\/bible\/nwt\/books\/mcr\/16323101\/\" data-bible=\"nwt\" data-targetverses=\"11003012,11010023,19072008\">+<\/a><\/span>\n<span class=\"parabreak\"><\/span><\/span>\n\n<span class=\"verse\" id=\"v11001038\"><span class=\"style-b first\"><sup class=\"verseNum\"><a href='\/en\/publications\/bible\/nwt\/books\/json\/html\/11001001-11001999#v11001038' data-anchor='#v11001038'>38\u00a0<\/a><\/sup>\u00a0Then Za\u02b9dok the priest, Nathan the prophet, Be\u00b7nai\u02b9ah<a class=\"xrefLink jsBibleLink\" id=\"xreflink16323134\" href=\"\/en\/publications\/bible\/nwt\/books\/mcr\/16323134\/\" data-bible=\"nwt\" data-targetverses=\"13027005\">+<\/a> the son of Je\u00b7hoi\u02b9a\u00b7da, and the Cher\u02b9e\u00b7thites and the Pel\u02b9e\u00b7thites<a class=\"xrefLink jsBibleLink\" id=\"xreflink16323147\" href=\"\/en\/publications\/bible\/nwt\/books\/mcr\/16323147\/\" data-bible=\"nwt\" data-targetverses=\"10015018,13018017\">+<\/a> went down and had Sol\u02b9o\u00b7mon ride on the mule of King David,<a class=\"xrefLink jsBibleLink\" id=\"xreflink16323168\" href=\"\/en\/publications\/bible\/nwt\/books\/mcr\/16323168\/\" data-bible=\"nwt\" data-targetverses=\"11001033,40021007\">+<\/a> and they brought him to Gi\u02b9hon.<a class=\"xrefLink jsBibleLink\" id=\"xreflink16323177\" href=\"\/en\/publications\/bible\/nwt\/books\/mcr\/16323177\/\" data-bible=\"nwt\" data-targetverses=\"14032030\">+<\/a><\/span><\/span>\n\n<span class=\"verse\" id=\"v11001039\"><span class=\"style-b\"><sup class=\"verseNum\"><a href='\/en\/publications\/bible\/nwt\/books\/json\/html\/11001001-11001999#v11001039' data-anchor='#v11001039'>39\u00a0<\/a><\/sup>\u00a0Za\u02b9dok the priest now took the horn of oil<a class=\"xrefLink jsBibleLink\" id=\"xreflink16323209\" href=\"\/en\/publications\/bible\/nwt\/books\/mcr\/16323209\/\" data-bible=\"nwt\" data-targetverses=\"2030023-2030025,9016013\">+<\/a> out of the tent<a class=\"xrefLink jsBibleLink\" id=\"xreflink16323222\" href=\"\/en\/publications\/bible\/nwt\/books\/mcr\/16323222\/\" data-bible=\"nwt\" data-targetverses=\"10006017\">+<\/a> and anointed Sol\u02b9o\u00b7mon,<a class=\"xrefLink jsBibleLink\" id=\"xreflink16323234\" href=\"\/en\/publications\/bible\/nwt\/books\/mcr\/16323234\/\" data-bible=\"nwt\" data-targetverses=\"13029022\">+<\/a> and they began to blow the horn, and all the people began shouting: \u201cLong live King Sol\u02b9o\u00b7mon!\u201d<\/span><\/span>\n\n<span class=\"verse\" id=\"v11001040\"><span class=\"style-b\"><sup class=\"verseNum\"><a href='\/en\/publications\/bible\/nwt\/books\/json\/html\/11001001-11001999#v11001040' data-anchor='#v11001040'>40\u00a0<\/a><\/sup>\u00a0After that all the people followed him and went up, playing flutes and rejoicing greatly, so that the earth was split open by their noise.<a class=\"xrefLink jsBibleLink\" id=\"xreflink16323261\" href=\"\/en\/publications\/bible\/nwt\/books\/mcr\/16323261\/\" data-bible=\"nwt\" data-targetverses=\"9004005\">+<\/a><\/span>\n<span class=\"parabreak\"><\/span><\/span>\n\n<span class=\"verse\" id=\"v11001041\"><span class=\"style-b first\"><sup class=\"verseNum\"><a href='\/en\/publications\/bible\/nwt\/books\/json\/html\/11001001-11001999#v11001041' data-anchor='#v11001041'>41\u00a0<\/a><\/sup>\u00a0Ad\u00b7o\u00b7ni\u02b9jah and all those invited by him heard it when they had finished eating.<a class=\"xrefLink jsBibleLink\" id=\"xreflink16323284\" href=\"\/en\/publications\/bible\/nwt\/books\/mcr\/16323284\/\" data-bible=\"nwt\" data-targetverses=\"11001009,11001025\">+<\/a> As soon as Jo\u02b9ab heard the sound of the horn, he said: \u201cWhy is there such a noisy uproar in the city?\u201d<\/span><\/span>\n\n<span class=\"verse\" id=\"v11001042\"><span class=\"style-b\"><sup class=\"verseNum\"><a href='\/en\/publications\/bible\/nwt\/books\/json\/html\/11001001-11001999#v11001042' data-anchor='#v11001042'>42\u00a0<\/a><\/sup>\u00a0While he was still speaking, Jon\u02b9a\u00b7than<a class=\"xrefLink jsBibleLink\" id=\"xreflink16323365\" href=\"\/en\/publications\/bible\/nwt\/books\/mcr\/16323365\/\" data-bible=\"nwt\" data-targetverses=\"10015036,10017017\">+<\/a> the son of A\u00b7bi\u02b9a\u00b7thar the priest came. Then Ad\u00b7o\u00b7ni\u02b9jah said: \u201cCome in, for you are a good<a class=\"footnoteLink\" id=\"footnotesource16323384\" href='\/en\/publications\/bible\/nwt\/books\/json\/html\/11001001-11001999#fn16323384' data-anchor='#fn16323384'>*<\/a> man, and you must bring good news.\u201d<\/span><\/span>\n\n<span class=\"verse\" id=\"v11001043\"><span class=\"style-b\"><sup class=\"verseNum\"><a href='\/en\/publications\/bible\/nwt\/books\/json\/html\/11001001-11001999#v11001043' data-anchor='#v11001043'>43\u00a0<\/a><\/sup>\u00a0But Jon\u02b9a\u00b7than answered Ad\u00b7o\u00b7ni\u02b9jah: \u201cNo! Our lord King David has made Sol\u02b9o\u00b7mon king.<\/span><\/span>\n\n<span class=\"verse\" id=\"v11001044\"><span class=\"style-b\"><sup class=\"verseNum\"><a href='\/en\/publications\/bible\/nwt\/books\/json\/html\/11001001-11001999#v11001044' data-anchor='#v11001044'>44\u00a0<\/a><\/sup>\u00a0The king sent with him Za\u02b9dok the priest, Nathan the prophet, Be\u00b7nai\u02b9ah the son of Je\u00b7hoi\u02b9a\u00b7da, and the Cher\u02b9e\u00b7thites and the Pel\u02b9e\u00b7thites, and they had him ride on the mule of the king.<a class=\"xrefLink jsBibleLink\" id=\"xreflink16323418\" href=\"\/en\/publications\/bible\/nwt\/books\/mcr\/16323418\/\" data-bible=\"nwt\" data-targetverses=\"11001033-11001034\">+<\/a><\/span><\/span>\n\n<span class=\"verse\" id=\"v11001045\"><span class=\"style-b\"><sup class=\"verseNum\"><a href='\/en\/publications\/bible\/nwt\/books\/json\/html\/11001001-11001999#v11001045' data-anchor='#v11001045'>45\u00a0<\/a><\/sup>\u00a0Then Za\u02b9dok the priest and Nathan the prophet anointed him as king in Gi\u02b9hon. After that they came up from there rejoicing, and the city is in an uproar. That was the noise that you heard.<\/span><\/span>\n\n<span class=\"verse\" id=\"v11001046\"><span class=\"style-b\"><sup class=\"verseNum\"><a href='\/en\/publications\/bible\/nwt\/books\/json\/html\/11001001-11001999#v11001046' data-anchor='#v11001046'>46\u00a0<\/a><\/sup>\u00a0Moreover, Sol\u02b9o\u00b7mon has sat down on the royal throne.<\/span><\/span>\n\n<span class=\"verse\" id=\"v11001047\"><span class=\"style-b\"><sup class=\"verseNum\"><a href='\/en\/publications\/bible\/nwt\/books\/json\/html\/11001001-11001999#v11001047' data-anchor='#v11001047'>47\u00a0<\/a><\/sup>\u00a0Another thing, the servants of the king have come in to congratulate our lord King David, saying, \u2018May your God make Sol\u02b9o\u00b7mon\u2019s name more splendid than your name, and may He make his throne greater than your throne!\u2019 At that the king bowed down on the bed.<\/span><\/span>\n\n<span class=\"verse\" id=\"v11001048\"><span class=\"style-b\"><sup class=\"verseNum\"><a href='\/en\/publications\/bible\/nwt\/books\/json\/html\/11001001-11001999#v11001048' data-anchor='#v11001048'>48\u00a0<\/a><\/sup>\u00a0And the king also said, \u2018May Jehovah the God of Israel be praised, who today has granted someone to sit on my throne and has allowed my own eyes to see it!\u2019\u201d<\/span>\n<span class=\"parabreak\"><\/span><\/span>\n\n<span class=\"verse\" id=\"v11001049\"><span class=\"style-b first\"><sup class=\"verseNum\"><a href='\/en\/publications\/bible\/nwt\/books\/json\/html\/11001001-11001999#v11001049' data-anchor='#v11001049'>49\u00a0<\/a><\/sup>\u00a0And all those invited by Ad\u00b7o\u00b7ni\u02b9jah became terrified, and each of them rose up and went his own way.<\/span><\/span>\n\n<span class=\"verse\" id=\"v11001050\"><span class=\"style-b\"><sup class=\"verseNum\"><a href='\/en\/publications\/bible\/nwt\/books\/json\/html\/11001001-11001999#v11001050' data-anchor='#v11001050'>50\u00a0<\/a><\/sup>\u00a0Ad\u00b7o\u00b7ni\u02b9jah was also afraid because of Sol\u02b9o\u00b7mon, so he got up and went and grabbed hold of the horns of the altar.<a class=\"xrefLink jsBibleLink\" id=\"xreflink16323521\" href=\"\/en\/publications\/bible\/nwt\/books\/mcr\/16323521\/\" data-bible=\"nwt\" data-targetverses=\"2021014,2038001-2038002,11002028\">+<\/a><\/span><\/span>\n\n<span class=\"verse\" id=\"v11001051\"><span class=\"style-b\"><sup class=\"verseNum\"><a href='\/en\/publications\/bible\/nwt\/books\/json\/html\/11001001-11001999#v11001051' data-anchor='#v11001051'>51\u00a0<\/a><\/sup>\u00a0The report was made to Sol\u02b9o\u00b7mon: \u201cHere Ad\u00b7o\u00b7ni\u02b9jah has become afraid of King Sol\u02b9o\u00b7mon; and he has taken hold of the horns of the altar, saying, \u2018Let King Sol\u02b9o\u00b7mon first swear to me that he will not put his servant to death by the sword.\u2019\u201d<\/span><\/span>\n\n<span class=\"verse\" id=\"v11001052\"><span class=\"style-b\"><sup class=\"verseNum\"><a href='\/en\/publications\/bible\/nwt\/books\/json\/html\/11001001-11001999#v11001052' data-anchor='#v11001052'>52\u00a0<\/a><\/sup>\u00a0To this Sol\u02b9o\u00b7mon said: \u201cIf he behaves in a worthy manner, not a single hair of his will fall to the ground; but if what is bad is found in him,<a class=\"xrefLink jsBibleLink\" id=\"xreflink16323563\" href=\"\/en\/publications\/bible\/nwt\/books\/mcr\/16323563\/\" data-bible=\"nwt\" data-targetverses=\"11002023\">+<\/a> he will have to die.\u201d<\/span><\/span>\n\n<span class=\"verse\" id=\"v11001053\"><span class=\"style-b\"><sup class=\"verseNum\"><a href='\/en\/publications\/bible\/nwt\/books\/json\/html\/11001001-11001999#v11001053' data-anchor='#v11001053'>53\u00a0<\/a><\/sup>\u00a0So King Sol\u02b9o\u00b7mon sent for him to be brought down from the altar. Then he came in and bowed down to King Sol\u02b9o\u00b7mon, after which Sol\u02b9o\u00b7mon said to him: \u201cGo to your own house.\u201d<\/span><span class=\"parabreak\"><\/span><\/span>\n\n","footnotes":"<div class=\"footnote\" id=\"fn16321954\"><a class=\"fnSourceLink\" href='\/en\/publications\/bible\/nwt\/books\/json\/html\/11001001-11001999#footnotesource16321954' data-anchor='#footnotesource16321954'>^&nbsp;<\/a><span class=\"\">Lit., \u201cdays.\u201d<\/span><\/div>\n\n<div class=\"footnote\" id=\"fn16322093\"><a class=\"fnSourceLink\" href='\/en\/publications\/bible\/nwt\/books\/json\/html\/11001001-11001999#footnotesource16322093' data-anchor='#footnotesource16322093'>^&nbsp;<\/a><span class=\"\">Or \u201churt his feelings; rebuked him.\u201d<\/span><\/div>\n\n<div class=\"footnote\" id=\"fn16322380\"><a class=\"fnSourceLink\" href='\/en\/publications\/bible\/nwt\/books\/json\/html\/11001001-11001999#footnotesource16322380' data-anchor='#footnotesource16322380'>^&nbsp;<\/a><span class=\"\">Or \u201cyour own soul and the soul of.\u201d<\/span><\/div>\n\n<div class=\"footnote\" id=\"fn16322843\"><a class=\"fnSourceLink\" href='\/en\/publications\/bible\/nwt\/books\/json\/html\/11001001-11001999#footnotesource16322843' data-anchor='#footnotesource16322843'>^&nbsp;<\/a><span class=\"\">Or \u201credeemed my soul.\u201d<\/span><\/div>\n\n<div class=\"footnote\" id=\"fn16322977\"><a class=\"fnSourceLink\" href='\/en\/publications\/bible\/nwt\/books\/json\/html\/11001001-11001999#footnotesource16322977' data-anchor='#footnotesource16322977'>^&nbsp;<\/a><span class=\"\">Or \u201cshe-mule.\u201d<\/span><\/div>\n\n<div class=\"footnote\" id=\"fn16323384\"><a class=\"fnSourceLink\" href='\/en\/publications\/bible\/nwt\/books\/json\/html\/11001001-11001999#footnotesource16323384' data-anchor='#footnotesource16323384'>^&nbsp;<\/a><span class=\"\">Or \u201cworthy.\u201d<\/span><\/div>\n\n"}}}