{"status":200,"currentLocale":"en","ranges":{"19063001-19063999":{"citation":"Psalms&nbsp;63:1-11","link":"https:\/\/www.jw.org\/en\/publications\/bible\/nwt\/books\/psalms\/63\/#v19063001-v19063011","validRange":"19063001-19063011","html":"<span class=\"verse\" id=\"v19063001\"><span class=\"style-l\"><span class=\"chapterNum\"><a href='\/en\/publications\/bible\/nwt\/books\/json\/html\/19063001-19063999#v19063001' data-anchor='#v19063001'>63 <\/a><\/span>\u00a0O God, you are my God, I keep looking for you.<a class=\"xrefLink jsBibleLink\" id=\"xreflink16328897\" href=\"\/en\/publications\/bible\/nwt\/books\/mcr\/16328897\/\" data-bible=\"nwt\" data-targetverses=\"23026009\">+<\/a><\/span><span class=\"parabreak\"><\/span>\n<span class=\"style-z\">I do thirst<a class=\"footnoteLink\" id=\"footnotesource16328931\" href='\/en\/publications\/bible\/nwt\/books\/json\/html\/19063001-19063999#fn16328931' data-anchor='#fn16328931'>*<\/a> for you.<a class=\"xrefLink jsBibleLink\" id=\"xreflink16328905\" href=\"\/en\/publications\/bible\/nwt\/books\/mcr\/16328905\/\" data-bible=\"nwt\" data-targetverses=\"19042002\">+<\/a><\/span><span class=\"parabreak\"><\/span>\n\n<span class=\"style-z\">I am<a class=\"footnoteLink\" id=\"footnotesource16328936\" href='\/en\/publications\/bible\/nwt\/books\/json\/html\/19063001-19063999#fn16328936' data-anchor='#fn16328936'>*<\/a> faint with longing for you<\/span>\n<span class=\"style-z\">In a dry and parched land, where there is no water.<a class=\"xrefLink jsBibleLink\" id=\"xreflink16328916\" href=\"\/en\/publications\/bible\/nwt\/books\/mcr\/16328916\/\" data-bible=\"nwt\" data-targetverses=\"19063000,19143006\">+<\/a><\/span>\n\n<span class=\"parabreak\"><\/span><\/span>\n\n<span class=\"verse\" id=\"v19063002\"><span class=\"style-l\">\u00a0<sup class=\"verseNum\"><a href='\/en\/publications\/bible\/nwt\/books\/json\/html\/19063001-19063999#v19063002' data-anchor='#v19063002'>2\u00a0<\/a><\/sup>\u00a0So I have looked upon you in the holy place;<\/span>\n<span class=\"style-z\">I have seen your strength and your glory.<a class=\"xrefLink jsBibleLink\" id=\"xreflink16328957\" href=\"\/en\/publications\/bible\/nwt\/books\/mcr\/16328957\/\" data-bible=\"nwt\" data-targetverses=\"13016028,19096006\">+<\/a><\/span>\n\n<span class=\"parabreak\"><\/span><\/span>\n\n<span class=\"verse\" id=\"v19063003\"><span class=\"style-l\">\u00a0<sup class=\"verseNum\"><a href='\/en\/publications\/bible\/nwt\/books\/json\/html\/19063001-19063999#v19063003' data-anchor='#v19063003'>3\u00a0<\/a><\/sup>\u00a0Because your loyal love is better than life,<a class=\"xrefLink jsBibleLink\" id=\"xreflink16328971\" href=\"\/en\/publications\/bible\/nwt\/books\/mcr\/16328971\/\" data-bible=\"nwt\" data-targetverses=\"19030005,19100005\">+<\/a><\/span>\n<span class=\"style-z\">My own lips will glorify you.<a class=\"xrefLink jsBibleLink\" id=\"xreflink16328985\" href=\"\/en\/publications\/bible\/nwt\/books\/mcr\/16328985\/\" data-bible=\"nwt\" data-targetverses=\"19066016-19066017\">+<\/a><\/span>\n\n<span class=\"parabreak\"><\/span><\/span>\n\n<span class=\"verse\" id=\"v19063004\"><span class=\"style-l\">\u00a0<sup class=\"verseNum\"><a href='\/en\/publications\/bible\/nwt\/books\/json\/html\/19063001-19063999#v19063004' data-anchor='#v19063004'>4\u00a0<\/a><\/sup>\u00a0Thus I will praise you all my life;<\/span>\n<span class=\"style-z\">In your name I will lift up my hands.<\/span>\n\n<span class=\"parabreak\"><\/span><\/span>\n\n<span class=\"verse\" id=\"v19063005\"><span class=\"style-l\">\u00a0<sup class=\"verseNum\"><a href='\/en\/publications\/bible\/nwt\/books\/json\/html\/19063001-19063999#v19063005' data-anchor='#v19063005'>5\u00a0<\/a><\/sup>\u00a0I am<a class=\"footnoteLink\" id=\"footnotesource16329031\" href='\/en\/publications\/bible\/nwt\/books\/json\/html\/19063001-19063999#fn16329031' data-anchor='#fn16329031'>*<\/a> satisfied with the best and choicest portion,<a class=\"footnoteLink\" id=\"footnotesource16329041\" href='\/en\/publications\/bible\/nwt\/books\/json\/html\/19063001-19063999#fn16329041' data-anchor='#fn16329041'>*<\/a><\/span>\n<span class=\"style-z\">So my mouth will praise you with joy on my lips.<a class=\"xrefLink jsBibleLink\" id=\"xreflink16329015\" href=\"\/en\/publications\/bible\/nwt\/books\/mcr\/16329015\/\" data-bible=\"nwt\" data-targetverses=\"19071023,19135003\">+<\/a><\/span>\n\n<span class=\"parabreak\"><\/span><\/span>\n\n<span class=\"verse\" id=\"v19063006\"><span class=\"style-l\">\u00a0<sup class=\"verseNum\"><a href='\/en\/publications\/bible\/nwt\/books\/json\/html\/19063001-19063999#v19063006' data-anchor='#v19063006'>6\u00a0<\/a><\/sup>\u00a0I remember you while upon my bed;<\/span>\n<span class=\"style-z\">I meditate on you during the watches of the night.<a class=\"xrefLink jsBibleLink\" id=\"xreflink16329059\" href=\"\/en\/publications\/bible\/nwt\/books\/mcr\/16329059\/\" data-bible=\"nwt\" data-targetverses=\"19119055,19119148\">+<\/a><\/span>\n\n<span class=\"parabreak\"><\/span><\/span>\n\n<span class=\"verse\" id=\"v19063007\"><span class=\"style-l\">\u00a0<sup class=\"verseNum\"><a href='\/en\/publications\/bible\/nwt\/books\/json\/html\/19063001-19063999#v19063007' data-anchor='#v19063007'>7\u00a0<\/a><\/sup>\u00a0For you are my helper,<a class=\"xrefLink jsBibleLink\" id=\"xreflink16329084\" href=\"\/en\/publications\/bible\/nwt\/books\/mcr\/16329084\/\" data-bible=\"nwt\" data-targetverses=\"9017037\">+<\/a><\/span>\n<span class=\"style-z\">And I shout joyfully in the shadow of your wings.<a class=\"xrefLink jsBibleLink\" id=\"xreflink16329095\" href=\"\/en\/publications\/bible\/nwt\/books\/mcr\/16329095\/\" data-bible=\"nwt\" data-targetverses=\"19005011,19057001,19061004\">+<\/a><\/span>\n\n<span class=\"parabreak\"><\/span><\/span>\n\n<span class=\"verse\" id=\"v19063008\"><span class=\"style-l\">\u00a0<sup class=\"verseNum\"><a href='\/en\/publications\/bible\/nwt\/books\/json\/html\/19063001-19063999#v19063008' data-anchor='#v19063008'>8\u00a0<\/a><\/sup>\u00a0I cling<a class=\"footnoteLink\" id=\"footnotesource16329141\" href='\/en\/publications\/bible\/nwt\/books\/json\/html\/19063001-19063999#fn16329141' data-anchor='#fn16329141'>*<\/a> to you;<\/span>\n<span class=\"style-z\">Your right hand keeps fast hold on me.<a class=\"xrefLink jsBibleLink\" id=\"xreflink16329122\" href=\"\/en\/publications\/bible\/nwt\/books\/mcr\/16329122\/\" data-bible=\"nwt\" data-targetverses=\"23041010\">+<\/a><\/span>\n\n<span class=\"parabreak\"><\/span><\/span>\n\n<span class=\"verse\" id=\"v19063009\"><span class=\"style-l\">\u00a0<sup class=\"verseNum\"><a href='\/en\/publications\/bible\/nwt\/books\/json\/html\/19063001-19063999#v19063009' data-anchor='#v19063009'>9\u00a0<\/a><\/sup>\u00a0But those who seek to destroy my life<a class=\"footnoteLink\" id=\"footnotesource16329160\" href='\/en\/publications\/bible\/nwt\/books\/json\/html\/19063001-19063999#fn16329160' data-anchor='#fn16329160'>*<\/a><\/span>\n<span class=\"style-z\">Will descend into the depths of the earth.<\/span>\n\n<span class=\"parabreak\"><\/span><\/span>\n\n<span class=\"verse\" id=\"v19063010\"><span class=\"style-l\"><sup class=\"verseNum\"><a href='\/en\/publications\/bible\/nwt\/books\/json\/html\/19063001-19063999#v19063010' data-anchor='#v19063010'>10\u00a0<\/a><\/sup>\u00a0They will be handed over to the power of the sword;<\/span>\n<span class=\"style-z\">They will become food for jackals.<a class=\"footnoteLink\" id=\"footnotesource16329176\" href='\/en\/publications\/bible\/nwt\/books\/json\/html\/19063001-19063999#fn16329176' data-anchor='#fn16329176'>*<\/a><\/span>\n\n<span class=\"parabreak\"><\/span><\/span>\n\n<span class=\"verse\" id=\"v19063011\"><span class=\"style-l\"><sup class=\"verseNum\"><a href='\/en\/publications\/bible\/nwt\/books\/json\/html\/19063001-19063999#v19063011' data-anchor='#v19063011'>11\u00a0<\/a><\/sup>\u00a0But the king will rejoice in God.<\/span><span class=\"parabreak\"><\/span>\n\n<span class=\"style-z\">Every person swearing by Him will exult,<a class=\"footnoteLink\" id=\"footnotesource16329193\" href='\/en\/publications\/bible\/nwt\/books\/json\/html\/19063001-19063999#fn16329193' data-anchor='#fn16329193'>*<\/a><\/span>\n<span class=\"style-z\">For the mouth of those speaking lies will be silenced.<\/span><span class=\"parabreak\"><\/span><\/span>\n\n","footnotes":"<div class=\"footnote\" id=\"fn16328931\"><a class=\"fnSourceLink\" href='\/en\/publications\/bible\/nwt\/books\/json\/html\/19063001-19063999#footnotesource16328931' data-anchor='#footnotesource16328931'>^&nbsp;<\/a><span class=\"\">Or \u201cMy soul thirsts.\u201d<\/span><\/div>\n\n<div class=\"footnote\" id=\"fn16328936\"><a class=\"fnSourceLink\" href='\/en\/publications\/bible\/nwt\/books\/json\/html\/19063001-19063999#footnotesource16328936' data-anchor='#footnotesource16328936'>^&nbsp;<\/a><span class=\"\">Lit., \u201cMy flesh is.\u201d<\/span><\/div>\n\n<div class=\"footnote\" id=\"fn16329031\"><a class=\"fnSourceLink\" href='\/en\/publications\/bible\/nwt\/books\/json\/html\/19063001-19063999#footnotesource16329031' data-anchor='#footnotesource16329031'>^&nbsp;<\/a><span class=\"\">Or \u201cMy soul is.\u201d<\/span><\/div>\n\n<div class=\"footnote\" id=\"fn16329041\"><a class=\"fnSourceLink\" href='\/en\/publications\/bible\/nwt\/books\/json\/html\/19063001-19063999#footnotesource16329041' data-anchor='#footnotesource16329041'>^&nbsp;<\/a><span class=\"\">Lit., \u201cas with fat and fatness.\u201d<\/span><\/div>\n\n<div class=\"footnote\" id=\"fn16329141\"><a class=\"fnSourceLink\" href='\/en\/publications\/bible\/nwt\/books\/json\/html\/19063001-19063999#footnotesource16329141' data-anchor='#footnotesource16329141'>^&nbsp;<\/a><span class=\"\">Or \u201cMy soul clings.\u201d<\/span><\/div>\n\n<div class=\"footnote\" id=\"fn16329160\"><a class=\"fnSourceLink\" href='\/en\/publications\/bible\/nwt\/books\/json\/html\/19063001-19063999#footnotesource16329160' data-anchor='#footnotesource16329160'>^&nbsp;<\/a><span class=\"\">Or \u201cdestroy my soul; kill me.\u201d<\/span><\/div>\n\n<div class=\"footnote\" id=\"fn16329176\"><a class=\"fnSourceLink\" href='\/en\/publications\/bible\/nwt\/books\/json\/html\/19063001-19063999#footnotesource16329176' data-anchor='#footnotesource16329176'>^&nbsp;<\/a><span class=\"\">Or \u201cfoxes.\u201d<\/span><\/div>\n\n<div class=\"footnote\" id=\"fn16329193\"><a class=\"fnSourceLink\" href='\/en\/publications\/bible\/nwt\/books\/json\/html\/19063001-19063999#footnotesource16329193' data-anchor='#footnotesource16329193'>^&nbsp;<\/a><span class=\"\">Or \u201cboast.\u201d<\/span><\/div>\n\n"}}}