{"status":200,"currentLocale":"en","ranges":{"40020001-40020999":{"citation":"Matthew&nbsp;20:1-34","link":"https:\/\/www.jw.org\/en\/publications\/bible\/nwt\/books\/matthew\/20\/#v40020001-v40020034","validRange":"40020001-40020034","html":"<span class=\"verse\" id=\"v40020001\"><span class=\"style-b\"><span class=\"chapterNum\"><a href='\/en\/publications\/bible\/nwt\/books\/json\/html\/40020001-40020999#v40020001' data-anchor='#v40020001'>20 <\/a><\/span>\u00a0\u201cFor the Kingdom of the heavens is like the master of a house who went out early in the morning to hire workers for his vineyard.<a class=\"xrefLink jsBibleLink\" id=\"xreflink16342921\" href=\"\/en\/publications\/bible\/nwt\/books\/mcr\/16342921\/\" data-bible=\"nwt\" data-targetverses=\"40021033\">+<\/a><\/span><\/span>\n\n<span class=\"verse\" id=\"v40020002\"><span class=\"style-b\"><sup class=\"verseNum\"><a href='\/en\/publications\/bible\/nwt\/books\/json\/html\/40020001-40020999#v40020002' data-anchor='#v40020002'>2\u00a0<\/a><\/sup>\u00a0After he had agreed with the workers for a de\u00b7nar\u02b9i\u00b7us<a class=\"footnoteLink\" id=\"footnotesource16342946\" href='\/en\/publications\/bible\/nwt\/books\/json\/html\/40020001-40020999#fn16342946' data-anchor='#fn16342946'>*<\/a> a day, he sent them into his vineyard.<\/span><\/span>\n\n<span class=\"verse\" id=\"v40020003\"><span class=\"style-b\"><sup class=\"verseNum\"><a href='\/en\/publications\/bible\/nwt\/books\/json\/html\/40020001-40020999#v40020003' data-anchor='#v40020003'>3\u00a0<\/a><\/sup>\u00a0Going out also about the third hour,<a class=\"footnoteLink\" id=\"footnotesource16342971\" href='\/en\/publications\/bible\/nwt\/books\/json\/html\/40020001-40020999#fn16342971' data-anchor='#fn16342971'>*<\/a> he saw others standing unemployed in the marketplace;<\/span><\/span>\n\n<span class=\"verse\" id=\"v40020004\"><span class=\"style-b\"><sup class=\"verseNum\"><a href='\/en\/publications\/bible\/nwt\/books\/json\/html\/40020001-40020999#v40020004' data-anchor='#v40020004'>4\u00a0<\/a><\/sup>\u00a0and to those he said, \u2018You too go into the vineyard, and I will give you whatever is fair.\u2019<\/span><\/span>\n\n<span class=\"verse\" id=\"v40020005\"><span class=\"style-b\"><sup class=\"verseNum\"><a href='\/en\/publications\/bible\/nwt\/books\/json\/html\/40020001-40020999#v40020005' data-anchor='#v40020005'>5\u00a0<\/a><\/sup>\u00a0So off they went. Again he went out about the sixth hour<a class=\"footnoteLink\" id=\"footnotesource16343002\" href='\/en\/publications\/bible\/nwt\/books\/json\/html\/40020001-40020999#fn16343002' data-anchor='#fn16343002'>*<\/a> and the ninth hour<a class=\"footnoteLink\" id=\"footnotesource16343013\" href='\/en\/publications\/bible\/nwt\/books\/json\/html\/40020001-40020999#fn16343013' data-anchor='#fn16343013'>*<\/a> and did likewise.<\/span><\/span>\n\n<span class=\"verse\" id=\"v40020006\"><span class=\"style-b\"><sup class=\"verseNum\"><a href='\/en\/publications\/bible\/nwt\/books\/json\/html\/40020001-40020999#v40020006' data-anchor='#v40020006'>6\u00a0<\/a><\/sup>\u00a0Finally, about the 11th hour,<a class=\"footnoteLink\" id=\"footnotesource16343108\" href='\/en\/publications\/bible\/nwt\/books\/json\/html\/40020001-40020999#fn16343108' data-anchor='#fn16343108'>*<\/a> he went out and found others standing around, and he said to them, \u2018Why have you been standing here all day unemployed?\u2019<\/span><\/span>\n\n<span class=\"verse\" id=\"v40020007\"><span class=\"style-b\"><sup class=\"verseNum\"><a href='\/en\/publications\/bible\/nwt\/books\/json\/html\/40020001-40020999#v40020007' data-anchor='#v40020007'>7\u00a0<\/a><\/sup>\u00a0They replied, \u2018Because nobody has hired us.\u2019 He said to them, \u2018You too go into the vineyard.\u2019<\/span>\n<span class=\"parabreak\"><\/span><\/span>\n\n<span class=\"verse\" id=\"v40020008\"><span class=\"style-b first\"><sup class=\"verseNum\"><a href='\/en\/publications\/bible\/nwt\/books\/json\/html\/40020001-40020999#v40020008' data-anchor='#v40020008'>8\u00a0<\/a><\/sup>\u00a0\u201cWhen evening came, the master of the vineyard said to his man in charge, \u2018Call the workers and pay them their wages,<a class=\"xrefLink jsBibleLink\" id=\"xreflink16343145\" href=\"\/en\/publications\/bible\/nwt\/books\/mcr\/16343145\/\" data-bible=\"nwt\" data-targetverses=\"3019013,5024014-5024015\">+<\/a> starting with the last and ending with the first.\u2019<\/span><\/span>\n\n<span class=\"verse\" id=\"v40020009\"><span class=\"style-b\"><sup class=\"verseNum\"><a href='\/en\/publications\/bible\/nwt\/books\/json\/html\/40020001-40020999#v40020009' data-anchor='#v40020009'>9\u00a0<\/a><\/sup>\u00a0When the 11th-hour men came, they each received a de\u00b7nar\u02b9i\u00b7us.<a class=\"footnoteLink\" id=\"footnotesource16343179\" href='\/en\/publications\/bible\/nwt\/books\/json\/html\/40020001-40020999#fn16343179' data-anchor='#fn16343179'>*<\/a><\/span><\/span>\n\n<span class=\"verse\" id=\"v40020010\"><span class=\"style-b\"><sup class=\"verseNum\"><a href='\/en\/publications\/bible\/nwt\/books\/json\/html\/40020001-40020999#v40020010' data-anchor='#v40020010'>10\u00a0<\/a><\/sup>\u00a0So when the first came, they assumed that they would receive more, but they too were paid at the rate of a de\u00b7nar\u02b9i\u00b7us.<a class=\"footnoteLink\" id=\"footnotesource16343201\" href='\/en\/publications\/bible\/nwt\/books\/json\/html\/40020001-40020999#fn16343201' data-anchor='#fn16343201'>*<\/a><\/span><\/span>\n\n<span class=\"verse\" id=\"v40020011\"><span class=\"style-b\"><sup class=\"verseNum\"><a href='\/en\/publications\/bible\/nwt\/books\/json\/html\/40020001-40020999#v40020011' data-anchor='#v40020011'>11\u00a0<\/a><\/sup>\u00a0On receiving it, they began to complain against the master of the house<\/span><\/span>\n\n<span class=\"verse\" id=\"v40020012\"><span class=\"style-b\"><sup class=\"verseNum\"><a href='\/en\/publications\/bible\/nwt\/books\/json\/html\/40020001-40020999#v40020012' data-anchor='#v40020012'>12\u00a0<\/a><\/sup>\u00a0and said, \u2018These last men put in one hour\u2019s work; still you made them equal to us who bore the burden of the day and the burning heat!\u2019<\/span><\/span>\n\n<span class=\"verse\" id=\"v40020013\"><span class=\"style-b\"><sup class=\"verseNum\"><a href='\/en\/publications\/bible\/nwt\/books\/json\/html\/40020001-40020999#v40020013' data-anchor='#v40020013'>13\u00a0<\/a><\/sup>\u00a0But he said in reply to one of them, \u2018Fellow, I do you no wrong. You agreed with me for a de\u00b7nar\u02b9i\u00b7us,<a class=\"footnoteLink\" id=\"footnotesource16343250\" href='\/en\/publications\/bible\/nwt\/books\/json\/html\/40020001-40020999#fn16343250' data-anchor='#fn16343250'>*<\/a> did you not?<a class=\"xrefLink jsBibleLink\" id=\"xreflink16343242\" href=\"\/en\/publications\/bible\/nwt\/books\/mcr\/16343242\/\" data-bible=\"nwt\" data-targetverses=\"40020002\">+<\/a><\/span><\/span>\n\n<span class=\"verse\" id=\"v40020014\"><span class=\"style-b\"><sup class=\"verseNum\"><a href='\/en\/publications\/bible\/nwt\/books\/json\/html\/40020001-40020999#v40020014' data-anchor='#v40020014'>14\u00a0<\/a><\/sup>\u00a0Take what is yours and go. I want to give to this last one the same as to you.<\/span><\/span>\n\n<span class=\"verse\" id=\"v40020015\"><span class=\"style-b\"><sup class=\"verseNum\"><a href='\/en\/publications\/bible\/nwt\/books\/json\/html\/40020001-40020999#v40020015' data-anchor='#v40020015'>15\u00a0<\/a><\/sup>\u00a0Do I not have the right to do what I want with my own things? Or is your eye envious<a class=\"footnoteLink\" id=\"footnotesource16343288\" href='\/en\/publications\/bible\/nwt\/books\/json\/html\/40020001-40020999#fn16343288' data-anchor='#fn16343288'>*<\/a> because I am good?\u2019<a class=\"footnoteLink\" id=\"footnotesource16343298\" href='\/en\/publications\/bible\/nwt\/books\/json\/html\/40020001-40020999#fn16343298' data-anchor='#fn16343298'>*<\/a><a class=\"xrefLink jsBibleLink\" id=\"xreflink16343276\" href=\"\/en\/publications\/bible\/nwt\/books\/mcr\/16343276\/\" data-bible=\"nwt\" data-targetverses=\"40006023\">+<\/a><\/span><\/span>\n\n<span class=\"verse\" id=\"v40020016\"><span class=\"style-b\"><sup class=\"verseNum\"><a href='\/en\/publications\/bible\/nwt\/books\/json\/html\/40020001-40020999#v40020016' data-anchor='#v40020016'>16\u00a0<\/a><\/sup>\u00a0In this way, the last ones will be first, and the first ones last.\u201d<a class=\"xrefLink jsBibleLink\" id=\"xreflink16343309\" href=\"\/en\/publications\/bible\/nwt\/books\/mcr\/16343309\/\" data-bible=\"nwt\" data-targetverses=\"40019030,41010031,42013030\">+<\/a><\/span>\n<span class=\"parabreak\"><\/span><\/span>\n\n<span class=\"verse\" id=\"v40020017\"><span class=\"style-b first\"><sup class=\"verseNum\"><a href='\/en\/publications\/bible\/nwt\/books\/json\/html\/40020001-40020999#v40020017' data-anchor='#v40020017'>17\u00a0<\/a><\/sup>\u00a0While going up to Jerusalem, Jesus took the 12 disciples aside privately and said to them on the road:<a class=\"xrefLink jsBibleLink\" id=\"xreflink16343332\" href=\"\/en\/publications\/bible\/nwt\/books\/mcr\/16343332\/\" data-bible=\"nwt\" data-targetverses=\"41010032,42018031\">+<\/a><\/span><\/span>\n\n<span class=\"verse\" id=\"v40020018\"><span class=\"style-b\"><sup class=\"verseNum\"><a href='\/en\/publications\/bible\/nwt\/books\/json\/html\/40020001-40020999#v40020018' data-anchor='#v40020018'>18\u00a0<\/a><\/sup>\u00a0\u201cLook! We are going up to Jerusalem, and the Son of man will be handed over to the chief priests and the scribes. They will condemn him to death<a class=\"xrefLink jsBibleLink\" id=\"xreflink16343360\" href=\"\/en\/publications\/bible\/nwt\/books\/mcr\/16343360\/\" data-bible=\"nwt\" data-targetverses=\"40016021,41010033-41010034,42009022,42018032-42018033\">+<\/a><\/span><\/span>\n\n<span class=\"verse\" id=\"v40020019\"><span class=\"style-b\"><sup class=\"verseNum\"><a href='\/en\/publications\/bible\/nwt\/books\/json\/html\/40020001-40020999#v40020019' data-anchor='#v40020019'>19\u00a0<\/a><\/sup>\u00a0and hand him over to men of the nations to be mocked and scourged and executed on a stake;<a class=\"xrefLink jsBibleLink\" id=\"xreflink16343392\" href=\"\/en\/publications\/bible\/nwt\/books\/mcr\/16343392\/\" data-bible=\"nwt\" data-targetverses=\"40027031,43019001\">+<\/a> and on the third day he will be raised up.\u201d<a class=\"xrefLink jsBibleLink\" id=\"xreflink16343401\" href=\"\/en\/publications\/bible\/nwt\/books\/mcr\/16343401\/\" data-bible=\"nwt\" data-targetverses=\"40017022-40017023,40028006,44010040,46015004\">+<\/a><\/span>\n<span class=\"parabreak\"><\/span><\/span>\n\n<span class=\"verse\" id=\"v40020020\"><span class=\"style-b first\"><sup class=\"verseNum\"><a href='\/en\/publications\/bible\/nwt\/books\/json\/html\/40020001-40020999#v40020020' data-anchor='#v40020020'>20\u00a0<\/a><\/sup>\u00a0Then the mother of the sons of Zeb\u02b9e\u00b7dee<a class=\"xrefLink jsBibleLink\" id=\"xreflink16343428\" href=\"\/en\/publications\/bible\/nwt\/books\/mcr\/16343428\/\" data-bible=\"nwt\" data-targetverses=\"40004021,40027055-40027056\">+<\/a> approached him with her sons, doing obeisance<a class=\"footnoteLink\" id=\"footnotesource16343445\" href='\/en\/publications\/bible\/nwt\/books\/json\/html\/40020001-40020999#fn16343445' data-anchor='#fn16343445'>*<\/a> and asking for something from him.<a class=\"xrefLink jsBibleLink\" id=\"xreflink16343436\" href=\"\/en\/publications\/bible\/nwt\/books\/mcr\/16343436\/\" data-bible=\"nwt\" data-targetverses=\"41010035-41010040\">+<\/a><\/span><\/span>\n\n<span class=\"verse\" id=\"v40020021\"><span class=\"style-b\"><sup class=\"verseNum\"><a href='\/en\/publications\/bible\/nwt\/books\/json\/html\/40020001-40020999#v40020021' data-anchor='#v40020021'>21\u00a0<\/a><\/sup>\u00a0He said to her: \u201cWhat do you want?\u201d She replied to him: \u201cGive the word that these two sons of mine may sit down, one at your right hand and one at your left, in your Kingdom.\u201d<a class=\"xrefLink jsBibleLink\" id=\"xreflink16343456\" href=\"\/en\/publications\/bible\/nwt\/books\/mcr\/16343456\/\" data-bible=\"nwt\" data-targetverses=\"40019028\">+<\/a><\/span><\/span>\n\n<span class=\"verse\" id=\"v40020022\"><span class=\"style-b\"><sup class=\"verseNum\"><a href='\/en\/publications\/bible\/nwt\/books\/json\/html\/40020001-40020999#v40020022' data-anchor='#v40020022'>22\u00a0<\/a><\/sup>\u00a0Jesus answered: \u201cYou do not know what you are asking for. Can you drink the cup that I am about to drink?\u201d<a class=\"xrefLink jsBibleLink\" id=\"xreflink16343555\" href=\"\/en\/publications\/bible\/nwt\/books\/mcr\/16343555\/\" data-bible=\"nwt\" data-targetverses=\"40026039,41010038,41014036,43018011\">+<\/a> They said to him: \u201cWe can.\u201d<\/span><\/span>\n\n<span class=\"verse\" id=\"v40020023\"><span class=\"style-b\"><sup class=\"verseNum\"><a href='\/en\/publications\/bible\/nwt\/books\/json\/html\/40020001-40020999#v40020023' data-anchor='#v40020023'>23\u00a0<\/a><\/sup>\u00a0He said to them: \u201cYou will indeed drink my cup,<a class=\"xrefLink jsBibleLink\" id=\"xreflink16343588\" href=\"\/en\/publications\/bible\/nwt\/books\/mcr\/16343588\/\" data-bible=\"nwt\" data-targetverses=\"44012002,45008017,47001007,66001009\">+<\/a> but to sit down at my right hand and at my left is not mine to give, but it belongs to those for whom it has been prepared by my Father.\u201d<a class=\"xrefLink jsBibleLink\" id=\"xreflink16343608\" href=\"\/en\/publications\/bible\/nwt\/books\/mcr\/16343608\/\" data-bible=\"nwt\" data-targetverses=\"41010039-41010040\">+<\/a><\/span>\n<span class=\"parabreak\"><\/span><\/span>\n\n<span class=\"verse\" id=\"v40020024\"><span class=\"style-b first\"><sup class=\"verseNum\"><a href='\/en\/publications\/bible\/nwt\/books\/json\/html\/40020001-40020999#v40020024' data-anchor='#v40020024'>24\u00a0<\/a><\/sup>\u00a0When the ten others heard about it, they became indignant at the two brothers.<a class=\"xrefLink jsBibleLink\" id=\"xreflink16343633\" href=\"\/en\/publications\/bible\/nwt\/books\/mcr\/16343633\/\" data-bible=\"nwt\" data-targetverses=\"41010041-41010045,42022024\">+<\/a><\/span><\/span>\n\n<span class=\"verse\" id=\"v40020025\"><span class=\"style-b\"><sup class=\"verseNum\"><a href='\/en\/publications\/bible\/nwt\/books\/json\/html\/40020001-40020999#v40020025' data-anchor='#v40020025'>25\u00a0<\/a><\/sup>\u00a0But Jesus called them to him and said: \u201cYou know that the rulers of the nations lord it over them and the great men wield authority over them.<a class=\"xrefLink jsBibleLink\" id=\"xreflink16343662\" href=\"\/en\/publications\/bible\/nwt\/books\/mcr\/16343662\/\" data-bible=\"nwt\" data-targetverses=\"41010042\">+<\/a><\/span><\/span>\n\n<span class=\"verse\" id=\"v40020026\"><span class=\"style-b\"><sup class=\"verseNum\"><a href='\/en\/publications\/bible\/nwt\/books\/json\/html\/40020001-40020999#v40020026' data-anchor='#v40020026'>26\u00a0<\/a><\/sup>\u00a0This must not be the way among you;<a class=\"xrefLink jsBibleLink\" id=\"xreflink16343690\" href=\"\/en\/publications\/bible\/nwt\/books\/mcr\/16343690\/\" data-bible=\"nwt\" data-targetverses=\"47001024,60005003\">+<\/a> but whoever wants to become great among you must be your minister,<a class=\"xrefLink jsBibleLink\" id=\"xreflink16343706\" href=\"\/en\/publications\/bible\/nwt\/books\/mcr\/16343706\/\" data-bible=\"nwt\" data-targetverses=\"40018004,40023011,41010043-41010044,42022026\">+<\/a><\/span><\/span>\n\n<span class=\"verse\" id=\"v40020027\"><span class=\"style-b\"><sup class=\"verseNum\"><a href='\/en\/publications\/bible\/nwt\/books\/json\/html\/40020001-40020999#v40020027' data-anchor='#v40020027'>27\u00a0<\/a><\/sup>\u00a0and whoever wants to be first among you must be your slave.<a class=\"xrefLink jsBibleLink\" id=\"xreflink16343831\" href=\"\/en\/publications\/bible\/nwt\/books\/mcr\/16343831\/\" data-bible=\"nwt\" data-targetverses=\"41009035\">+<\/a><\/span><\/span>\n\n<span class=\"verse\" id=\"v40020028\"><span class=\"style-b\"><sup class=\"verseNum\"><a href='\/en\/publications\/bible\/nwt\/books\/json\/html\/40020001-40020999#v40020028' data-anchor='#v40020028'>28\u00a0<\/a><\/sup>\u00a0Just as the Son of man came, not to be ministered to, but to minister<a class=\"xrefLink jsBibleLink\" id=\"xreflink16343862\" href=\"\/en\/publications\/bible\/nwt\/books\/mcr\/16343862\/\" data-bible=\"nwt\" data-targetverses=\"42022027,43013014,50002007\">+<\/a> and to give his life<a class=\"footnoteLink\" id=\"footnotesource16343909\" href='\/en\/publications\/bible\/nwt\/books\/json\/html\/40020001-40020999#fn16343909' data-anchor='#fn16343909'>*<\/a> as a ransom in exchange for many.\u201d<a class=\"xrefLink jsBibleLink\" id=\"xreflink16343888\" href=\"\/en\/publications\/bible\/nwt\/books\/mcr\/16343888\/\" data-bible=\"nwt\" data-targetverses=\"23053011,41010045,54002005-54002006,56002013-56002014,58009028\">+<\/a><\/span>\n<span class=\"parabreak\"><\/span><\/span>\n\n<span class=\"verse\" id=\"v40020029\"><span class=\"style-b first\"><sup class=\"verseNum\"><a href='\/en\/publications\/bible\/nwt\/books\/json\/html\/40020001-40020999#v40020029' data-anchor='#v40020029'>29\u00a0<\/a><\/sup>\u00a0As they were going out of Jer\u02b9i\u00b7cho, a large crowd followed him.<\/span><\/span>\n\n<span class=\"verse\" id=\"v40020030\"><span class=\"style-b\"><sup class=\"verseNum\"><a href='\/en\/publications\/bible\/nwt\/books\/json\/html\/40020001-40020999#v40020030' data-anchor='#v40020030'>30\u00a0<\/a><\/sup>\u00a0And look! two blind men sitting beside the road heard that Jesus was passing by and cried out: \u201cLord, have mercy on us, Son of David!\u201d<a class=\"xrefLink jsBibleLink\" id=\"xreflink16343952\" href=\"\/en\/publications\/bible\/nwt\/books\/mcr\/16343952\/\" data-bible=\"nwt\" data-targetverses=\"40009027,41010046-41010052,42018035-42018043\">+<\/a><\/span><\/span>\n\n<span class=\"verse\" id=\"v40020031\"><span class=\"style-b\"><sup class=\"verseNum\"><a href='\/en\/publications\/bible\/nwt\/books\/json\/html\/40020001-40020999#v40020031' data-anchor='#v40020031'>31\u00a0<\/a><\/sup>\u00a0But the crowd rebuked them, telling them to keep silent; yet they cried all the louder, saying: \u201cLord, have mercy on us, Son of David!\u201d<\/span><\/span>\n\n<span class=\"verse\" id=\"v40020032\"><span class=\"style-b\"><sup class=\"verseNum\"><a href='\/en\/publications\/bible\/nwt\/books\/json\/html\/40020001-40020999#v40020032' data-anchor='#v40020032'>32\u00a0<\/a><\/sup>\u00a0So Jesus stopped, called them, and said: \u201cWhat do you want me to do for you?\u201d<\/span><\/span>\n\n<span class=\"verse\" id=\"v40020033\"><span class=\"style-b\"><sup class=\"verseNum\"><a href='\/en\/publications\/bible\/nwt\/books\/json\/html\/40020001-40020999#v40020033' data-anchor='#v40020033'>33\u00a0<\/a><\/sup>\u00a0They said to him: \u201cLord, let our eyes be opened.\u201d<\/span><\/span>\n\n<span class=\"verse\" id=\"v40020034\"><span class=\"style-b\"><sup class=\"verseNum\"><a href='\/en\/publications\/bible\/nwt\/books\/json\/html\/40020001-40020999#v40020034' data-anchor='#v40020034'>34\u00a0<\/a><\/sup>\u00a0Moved with pity, Jesus touched their eyes,<a class=\"xrefLink jsBibleLink\" id=\"xreflink16344030\" href=\"\/en\/publications\/bible\/nwt\/books\/mcr\/16344030\/\" data-bible=\"nwt\" data-targetverses=\"40009029\">+<\/a> and immediately they recovered their sight, and they followed him.<\/span><span class=\"parabreak\"><\/span><\/span>\n\n","footnotes":"<div class=\"footnote\" id=\"fn16342946\"><a class=\"fnSourceLink\" href='\/en\/publications\/bible\/nwt\/books\/json\/html\/40020001-40020999#footnotesource16342946' data-anchor='#footnotesource16342946'>^&nbsp;<\/a><span class=\"\">See <a class='it pubSym-nwt' data-page-id=\"mid1001061236\" href='\/en\/publications\/bible\/nwt\/appendix-b\/bible-currency-and-weight\/'>App.\u00a0B14<\/a>.<\/span><\/div>\n\n<div class=\"footnote\" id=\"fn16342971\"><a class=\"fnSourceLink\" href='\/en\/publications\/bible\/nwt\/books\/json\/html\/40020001-40020999#footnotesource16342971' data-anchor='#footnotesource16342971'>^&nbsp;<\/a><span class=\"\">That is, about 9:00 a.m.<\/span><\/div>\n\n<div class=\"footnote\" id=\"fn16343002\"><a class=\"fnSourceLink\" href='\/en\/publications\/bible\/nwt\/books\/json\/html\/40020001-40020999#footnotesource16343002' data-anchor='#footnotesource16343002'>^&nbsp;<\/a><span class=\"\">That is, about 12:00 noon.<\/span><\/div>\n\n<div class=\"footnote\" id=\"fn16343013\"><a class=\"fnSourceLink\" href='\/en\/publications\/bible\/nwt\/books\/json\/html\/40020001-40020999#footnotesource16343013' data-anchor='#footnotesource16343013'>^&nbsp;<\/a><span class=\"\">That is, about 3:00 p.m.<\/span><\/div>\n\n<div class=\"footnote\" id=\"fn16343108\"><a class=\"fnSourceLink\" href='\/en\/publications\/bible\/nwt\/books\/json\/html\/40020001-40020999#footnotesource16343108' data-anchor='#footnotesource16343108'>^&nbsp;<\/a><span class=\"\">That is, about 5:00 p.m.<\/span><\/div>\n\n<div class=\"footnote\" id=\"fn16343179\"><a class=\"fnSourceLink\" href='\/en\/publications\/bible\/nwt\/books\/json\/html\/40020001-40020999#footnotesource16343179' data-anchor='#footnotesource16343179'>^&nbsp;<\/a><span class=\"\">See <a class='it pubSym-nwt' data-page-id=\"mid1001061236\" href='\/en\/publications\/bible\/nwt\/appendix-b\/bible-currency-and-weight\/'>App.\u00a0B14<\/a>.<\/span><\/div>\n\n<div class=\"footnote\" id=\"fn16343201\"><a class=\"fnSourceLink\" href='\/en\/publications\/bible\/nwt\/books\/json\/html\/40020001-40020999#footnotesource16343201' data-anchor='#footnotesource16343201'>^&nbsp;<\/a><span class=\"\">See <a class='it pubSym-nwt' data-page-id=\"mid1001061236\" href='\/en\/publications\/bible\/nwt\/appendix-b\/bible-currency-and-weight\/'>App.\u00a0B14<\/a>.<\/span><\/div>\n\n<div class=\"footnote\" id=\"fn16343250\"><a class=\"fnSourceLink\" href='\/en\/publications\/bible\/nwt\/books\/json\/html\/40020001-40020999#footnotesource16343250' data-anchor='#footnotesource16343250'>^&nbsp;<\/a><span class=\"\">See <a class='it pubSym-nwt' data-page-id=\"mid1001061236\" href='\/en\/publications\/bible\/nwt\/appendix-b\/bible-currency-and-weight\/'>App.\u00a0B14<\/a>.<\/span><\/div>\n\n<div class=\"footnote\" id=\"fn16343288\"><a class=\"fnSourceLink\" href='\/en\/publications\/bible\/nwt\/books\/json\/html\/40020001-40020999#footnotesource16343288' data-anchor='#footnotesource16343288'>^&nbsp;<\/a><span class=\"\">Lit., \u201cbad; wicked.\u201d<\/span><\/div>\n\n<div class=\"footnote\" id=\"fn16343298\"><a class=\"fnSourceLink\" href='\/en\/publications\/bible\/nwt\/books\/json\/html\/40020001-40020999#footnotesource16343298' data-anchor='#footnotesource16343298'>^&nbsp;<\/a><span class=\"\">Or \u201cgenerous.\u201d<\/span><\/div>\n\n<div class=\"footnote\" id=\"fn16343445\"><a class=\"fnSourceLink\" href='\/en\/publications\/bible\/nwt\/books\/json\/html\/40020001-40020999#footnotesource16343445' data-anchor='#footnotesource16343445'>^&nbsp;<\/a><span class=\"\">Or \u201cbowing down.\u201d<\/span><\/div>\n\n<div class=\"footnote\" id=\"fn16343909\"><a class=\"fnSourceLink\" href='\/en\/publications\/bible\/nwt\/books\/json\/html\/40020001-40020999#footnotesource16343909' data-anchor='#footnotesource16343909'>^&nbsp;<\/a><span class=\"\">Or \u201csoul.\u201d<\/span><\/div>\n\n"}}}