{"status":200,"currentLocale":"en","ranges":{"8002001-8002999":{"citation":"Ruth&nbsp;2:1-23","link":"https:\/\/www.jw.org\/en\/publications\/bible\/nwt\/books\/ruth\/2\/#v8002001-v8002023","validRange":"8002001-8002023","html":"<span class=\"verse\" id=\"v8002001\"><span class=\"style-b\"><span class=\"chapterNum\"><a href='\/en\/publications\/bible\/nwt\/books\/json\/html\/8002001-8002999#v8002001' data-anchor='#v8002001'>2 <\/a><\/span>\u00a0Now Na\u00b7o\u02b9mi had a relative on her husband\u2019s side who was very wealthy; his name was Bo\u02b9az,<a class=\"xrefLink jsBibleLink\" id=\"xreflink16320186\" href=\"\/en\/publications\/bible\/nwt\/books\/mcr\/16320186\/\" data-bible=\"nwt\" data-targetverses=\"8002020,8004021-8004022,40001005,42003023,42003032\">+<\/a> and he was of the family of E\u00b7lim\u02b9e\u00b7lech.<\/span>\n<span class=\"parabreak\"><\/span><\/span>\n\n<span class=\"verse\" id=\"v8002002\"><span class=\"style-b first\"><sup class=\"verseNum\"><a href='\/en\/publications\/bible\/nwt\/books\/json\/html\/8002001-8002999#v8002002' data-anchor='#v8002002'>2\u00a0<\/a><\/sup>\u00a0Ruth the Mo\u02b9ab\u00b7i\u00b7tess said to Na\u00b7o\u02b9mi: \u201cLet me go out, please, to the fields and glean<a class=\"xrefLink jsBibleLink\" id=\"xreflink16320207\" href=\"\/en\/publications\/bible\/nwt\/books\/mcr\/16320207\/\" data-bible=\"nwt\" data-targetverses=\"3023022,5024019\">+<\/a> among the ears of grain behind whoever looks on me with favor.\u201d So Na\u00b7o\u02b9mi said to her: \u201cGo, my daughter.\u201d<\/span><\/span>\n\n<span class=\"verse\" id=\"v8002003\"><span class=\"style-b\"><sup class=\"verseNum\"><a href='\/en\/publications\/bible\/nwt\/books\/json\/html\/8002001-8002999#v8002003' data-anchor='#v8002003'>3\u00a0<\/a><\/sup>\u00a0At that she went out and began to glean in the field behind the harvesters. By chance she came upon a plot of land belonging to Bo\u02b9az,<a class=\"xrefLink jsBibleLink\" id=\"xreflink16320230\" href=\"\/en\/publications\/bible\/nwt\/books\/mcr\/16320230\/\" data-bible=\"nwt\" data-targetverses=\"8002020\">+<\/a> who was of the family of E\u00b7lim\u02b9e\u00b7lech.<a class=\"xrefLink jsBibleLink\" id=\"xreflink16320240\" href=\"\/en\/publications\/bible\/nwt\/books\/mcr\/16320240\/\" data-bible=\"nwt\" data-targetverses=\"8001002\">+<\/a><\/span><\/span>\n\n<span class=\"verse\" id=\"v8002004\"><span class=\"style-b\"><sup class=\"verseNum\"><a href='\/en\/publications\/bible\/nwt\/books\/json\/html\/8002001-8002999#v8002004' data-anchor='#v8002004'>4\u00a0<\/a><\/sup>\u00a0Just then Bo\u02b9az arrived from Beth\u02b9le\u00b7hem and said to the harvesters: \u201cJehovah be with you.\u201d And they replied: \u201cJehovah bless you.\u201d<\/span>\n<span class=\"parabreak\"><\/span><\/span>\n\n<span class=\"verse\" id=\"v8002005\"><span class=\"style-b first\"><sup class=\"verseNum\"><a href='\/en\/publications\/bible\/nwt\/books\/json\/html\/8002001-8002999#v8002005' data-anchor='#v8002005'>5\u00a0<\/a><\/sup>\u00a0Bo\u02b9az then asked the young man in charge of the harvesters: \u201cTo whom does this young woman belong?\u201d<\/span><\/span>\n\n<span class=\"verse\" id=\"v8002006\"><span class=\"style-b\"><sup class=\"verseNum\"><a href='\/en\/publications\/bible\/nwt\/books\/json\/html\/8002001-8002999#v8002006' data-anchor='#v8002006'>6\u00a0<\/a><\/sup>\u00a0The young man in charge of the harvesters answered: \u201cThe young woman is a Mo\u02b9ab\u00b7i\u00b7tess<a class=\"xrefLink jsBibleLink\" id=\"xreflink16320291\" href=\"\/en\/publications\/bible\/nwt\/books\/mcr\/16320291\/\" data-bible=\"nwt\" data-targetverses=\"8001003-8001004\">+<\/a> who returned with Na\u00b7o\u02b9mi from the fields of Mo\u02b9ab.<a class=\"xrefLink jsBibleLink\" id=\"xreflink16320308\" href=\"\/en\/publications\/bible\/nwt\/books\/mcr\/16320308\/\" data-bible=\"nwt\" data-targetverses=\"8001016,8001022\">+<\/a><\/span><\/span>\n\n<span class=\"verse\" id=\"v8002007\"><span class=\"style-b\"><sup class=\"verseNum\"><a href='\/en\/publications\/bible\/nwt\/books\/json\/html\/8002001-8002999#v8002007' data-anchor='#v8002007'>7\u00a0<\/a><\/sup>\u00a0She asked, \u2018Please, may I glean<a class=\"xrefLink jsBibleLink\" id=\"xreflink16320331\" href=\"\/en\/publications\/bible\/nwt\/books\/mcr\/16320331\/\" data-bible=\"nwt\" data-targetverses=\"3023022,5024019\">+<\/a> and gather among the cut-off ears<a class=\"footnoteLink\" id=\"footnotesource16320354\" href='\/en\/publications\/bible\/nwt\/books\/json\/html\/8002001-8002999#fn16320354' data-anchor='#fn16320354'>*<\/a> of grain left behind by the harvesters?\u2019 And she has been on her feet since she came this morning until just now, when she sat in the shelter for a short rest.\u201d<\/span>\n<span class=\"parabreak\"><\/span><\/span>\n\n<span class=\"verse\" id=\"v8002008\"><span class=\"style-b first\"><sup class=\"verseNum\"><a href='\/en\/publications\/bible\/nwt\/books\/json\/html\/8002001-8002999#v8002008' data-anchor='#v8002008'>8\u00a0<\/a><\/sup>\u00a0Then Bo\u02b9az said to Ruth: \u201cListen, my daughter. Do not go away to glean in another field, and do not go anywhere else; stay close by my young women.<a class=\"xrefLink jsBibleLink\" id=\"xreflink16320373\" href=\"\/en\/publications\/bible\/nwt\/books\/mcr\/16320373\/\" data-bible=\"nwt\" data-targetverses=\"8002022\">+<\/a><\/span><\/span>\n\n<span class=\"verse\" id=\"v8002009\"><span class=\"style-b\"><sup class=\"verseNum\"><a href='\/en\/publications\/bible\/nwt\/books\/json\/html\/8002001-8002999#v8002009' data-anchor='#v8002009'>9\u00a0<\/a><\/sup>\u00a0Keep your eyes on the field that they harvest, and go with them. I have commanded the young men not to touch<a class=\"footnoteLink\" id=\"footnotesource16320397\" href='\/en\/publications\/bible\/nwt\/books\/json\/html\/8002001-8002999#fn16320397' data-anchor='#fn16320397'>*<\/a> you. When you are thirsty, go to the water jars and drink from what the young men have drawn.\u201d<\/span>\n<span class=\"parabreak\"><\/span><\/span>\n\n<span class=\"verse\" id=\"v8002010\"><span class=\"style-b first\"><sup class=\"verseNum\"><a href='\/en\/publications\/bible\/nwt\/books\/json\/html\/8002001-8002999#v8002010' data-anchor='#v8002010'>10\u00a0<\/a><\/sup>\u00a0At that she fell facedown and bowed down to the ground and said to him: \u201cHow have I found favor in your eyes, and why have you taken notice of me, when I am a foreigner?\u201d<a class=\"xrefLink jsBibleLink\" id=\"xreflink16320416\" href=\"\/en\/publications\/bible\/nwt\/books\/mcr\/16320416\/\" data-bible=\"nwt\" data-targetverses=\"2023009,3019034\">+<\/a><\/span><\/span>\n\n<span class=\"verse\" id=\"v8002011\"><span class=\"style-b\"><sup class=\"verseNum\"><a href='\/en\/publications\/bible\/nwt\/books\/json\/html\/8002001-8002999#v8002011' data-anchor='#v8002011'>11\u00a0<\/a><\/sup>\u00a0Bo\u02b9az answered her: \u201cA full report was made to me of all you have done for your mother-in-law after the death of your husband and how you left your father and your mother and the land of your relatives to go to a people whom you had not known before.<a class=\"xrefLink jsBibleLink\" id=\"xreflink16320444\" href=\"\/en\/publications\/bible\/nwt\/books\/mcr\/16320444\/\" data-bible=\"nwt\" data-targetverses=\"8001014,8001016\">+<\/a><\/span><\/span>\n\n<span class=\"verse\" id=\"v8002012\"><span class=\"style-b\"><sup class=\"verseNum\"><a href='\/en\/publications\/bible\/nwt\/books\/json\/html\/8002001-8002999#v8002012' data-anchor='#v8002012'>12\u00a0<\/a><\/sup>\u00a0May Jehovah reward you for what you have done,<a class=\"xrefLink jsBibleLink\" id=\"xreflink16320479\" href=\"\/en\/publications\/bible\/nwt\/books\/mcr\/16320479\/\" data-bible=\"nwt\" data-targetverses=\"8004011,8004017,40001005,40001016\">+<\/a> and may there be a perfect wage<a class=\"footnoteLink\" id=\"footnotesource16320538\" href='\/en\/publications\/bible\/nwt\/books\/json\/html\/8002001-8002999#fn16320538' data-anchor='#fn16320538'>*<\/a> for you from Jehovah the God of Israel, under whose wings you have come to seek refuge.\u201d<a class=\"xrefLink jsBibleLink\" id=\"xreflink16320507\" href=\"\/en\/publications\/bible\/nwt\/books\/mcr\/16320507\/\" data-bible=\"nwt\" data-targetverses=\"19017008,19036007,19057001,19063007\">+<\/a><\/span><\/span>\n\n<span class=\"verse\" id=\"v8002013\"><span class=\"style-b\"><sup class=\"verseNum\"><a href='\/en\/publications\/bible\/nwt\/books\/json\/html\/8002001-8002999#v8002013' data-anchor='#v8002013'>13\u00a0<\/a><\/sup>\u00a0To this she said: \u201cLet me find favor in your eyes, my lord, because you have comforted me and spoken reassuringly to<a class=\"footnoteLink\" id=\"footnotesource16320563\" href='\/en\/publications\/bible\/nwt\/books\/json\/html\/8002001-8002999#fn16320563' data-anchor='#fn16320563'>*<\/a> your servant, although I am not even one of your servants.\u201d<\/span>\n<span class=\"parabreak\"><\/span><\/span>\n\n<span class=\"verse\" id=\"v8002014\"><span class=\"style-b first\"><sup class=\"verseNum\"><a href='\/en\/publications\/bible\/nwt\/books\/json\/html\/8002001-8002999#v8002014' data-anchor='#v8002014'>14\u00a0<\/a><\/sup>\u00a0Bo\u02b9az said to her at mealtime: \u201cCome here, eat some of the bread, and dip your piece in the vinegar.\u201d So she sat down beside the harvesters. He then handed her some roasted grain, and she ate and was satisfied, and she had something left over.<\/span><\/span>\n\n<span class=\"verse\" id=\"v8002015\"><span class=\"style-b\"><sup class=\"verseNum\"><a href='\/en\/publications\/bible\/nwt\/books\/json\/html\/8002001-8002999#v8002015' data-anchor='#v8002015'>15\u00a0<\/a><\/sup>\u00a0When she got up to glean,<a class=\"xrefLink jsBibleLink\" id=\"xreflink16320605\" href=\"\/en\/publications\/bible\/nwt\/books\/mcr\/16320605\/\" data-bible=\"nwt\" data-targetverses=\"3019009,8002002\">+<\/a> Bo\u02b9az commanded his young men: \u201cLet her glean even among the cut-off ears<a class=\"footnoteLink\" id=\"footnotesource16320645\" href='\/en\/publications\/bible\/nwt\/books\/json\/html\/8002001-8002999#fn16320645' data-anchor='#fn16320645'>*<\/a> of grain, and do not mistreat her.<a class=\"xrefLink jsBibleLink\" id=\"xreflink16320627\" href=\"\/en\/publications\/bible\/nwt\/books\/mcr\/16320627\/\" data-bible=\"nwt\" data-targetverses=\"8002009\">+<\/a><\/span><\/span>\n\n<span class=\"verse\" id=\"v8002016\"><span class=\"style-b\"><sup class=\"verseNum\"><a href='\/en\/publications\/bible\/nwt\/books\/json\/html\/8002001-8002999#v8002016' data-anchor='#v8002016'>16\u00a0<\/a><\/sup>\u00a0You should also be sure to pull out some ears of grain from the bundles for her and leave them behind for her to glean, and do not say anything to stop her.\u201d<\/span>\n<span class=\"parabreak\"><\/span><\/span>\n\n<span class=\"verse\" id=\"v8002017\"><span class=\"style-b first\"><sup class=\"verseNum\"><a href='\/en\/publications\/bible\/nwt\/books\/json\/html\/8002001-8002999#v8002017' data-anchor='#v8002017'>17\u00a0<\/a><\/sup>\u00a0So she continued to glean in the field until evening.<a class=\"xrefLink jsBibleLink\" id=\"xreflink16320681\" href=\"\/en\/publications\/bible\/nwt\/books\/mcr\/16320681\/\" data-bible=\"nwt\" data-targetverses=\"8002007\">+<\/a> When she beat out what she had gleaned, it came to about an e\u02b9phah<a class=\"footnoteLink\" id=\"footnotesource16320703\" href='\/en\/publications\/bible\/nwt\/books\/json\/html\/8002001-8002999#fn16320703' data-anchor='#fn16320703'>*<\/a> of barley.<\/span><\/span>\n\n<span class=\"verse\" id=\"v8002018\"><span class=\"style-b\"><sup class=\"verseNum\"><a href='\/en\/publications\/bible\/nwt\/books\/json\/html\/8002001-8002999#v8002018' data-anchor='#v8002018'>18\u00a0<\/a><\/sup>\u00a0Then she took it and went into the city, and her mother-in-law saw what she had gleaned. Ruth also took out and gave to her the food that was left over<a class=\"xrefLink jsBibleLink\" id=\"xreflink16320722\" href=\"\/en\/publications\/bible\/nwt\/books\/mcr\/16320722\/\" data-bible=\"nwt\" data-targetverses=\"8002014\">+<\/a> after she had eaten her fill.<\/span>\n<span class=\"parabreak\"><\/span><\/span>\n\n<span class=\"verse\" id=\"v8002019\"><span class=\"style-b first\"><sup class=\"verseNum\"><a href='\/en\/publications\/bible\/nwt\/books\/json\/html\/8002001-8002999#v8002019' data-anchor='#v8002019'>19\u00a0<\/a><\/sup>\u00a0Her mother-in-law then said to her: \u201cWhere did you glean today? Where did you work? May the one who took notice of you be blessed.\u201d<a class=\"xrefLink jsBibleLink\" id=\"xreflink16320748\" href=\"\/en\/publications\/bible\/nwt\/books\/mcr\/16320748\/\" data-bible=\"nwt\" data-targetverses=\"19041001\">+<\/a> So she told her mother-in-law about whom she had worked with, saying: \u201cThe name of the man I worked with today is Bo\u02b9az.\u201d<\/span><\/span>\n\n<span class=\"verse\" id=\"v8002020\"><span class=\"style-b\"><sup class=\"verseNum\"><a href='\/en\/publications\/bible\/nwt\/books\/json\/html\/8002001-8002999#v8002020' data-anchor='#v8002020'>20\u00a0<\/a><\/sup>\u00a0At that Na\u00b7o\u02b9mi said to her daughter-in-law: \u201cMay he be blessed by Jehovah, who has not failed in his loyal love toward the living and the dead.\u201d<a class=\"xrefLink jsBibleLink\" id=\"xreflink16320777\" href=\"\/en\/publications\/bible\/nwt\/books\/mcr\/16320777\/\" data-bible=\"nwt\" data-targetverses=\"2034006,8001008,19036007\">+<\/a> Na\u00b7o\u02b9mi continued: \u201cThe man is related to us.<a class=\"xrefLink jsBibleLink\" id=\"xreflink16320810\" href=\"\/en\/publications\/bible\/nwt\/books\/mcr\/16320810\/\" data-bible=\"nwt\" data-targetverses=\"8002001\">+<\/a> He is one of our repurchasers.\u201d<a class=\"footnoteLink\" id=\"footnotesource16320876\" href='\/en\/publications\/bible\/nwt\/books\/json\/html\/8002001-8002999#fn16320876' data-anchor='#fn16320876'>*<\/a><a class=\"xrefLink jsBibleLink\" id=\"xreflink16320828\" href=\"\/en\/publications\/bible\/nwt\/books\/mcr\/16320828\/\" data-bible=\"nwt\" data-targetverses=\"3025025,5025005-5025006,8003009,8003012\">+<\/a><\/span><\/span>\n\n<span class=\"verse\" id=\"v8002021\"><span class=\"style-b\"><sup class=\"verseNum\"><a href='\/en\/publications\/bible\/nwt\/books\/json\/html\/8002001-8002999#v8002021' data-anchor='#v8002021'>21\u00a0<\/a><\/sup>\u00a0Then Ruth the Mo\u02b9ab\u00b7i\u00b7tess said: \u201cHe also told me, \u2018Stay close by my young people until they have finished my entire harvest.\u2019\u201d<a class=\"xrefLink jsBibleLink\" id=\"xreflink16320907\" href=\"\/en\/publications\/bible\/nwt\/books\/mcr\/16320907\/\" data-bible=\"nwt\" data-targetverses=\"8002008\">+<\/a><\/span><\/span>\n\n<span class=\"verse\" id=\"v8002022\"><span class=\"style-b\"><sup class=\"verseNum\"><a href='\/en\/publications\/bible\/nwt\/books\/json\/html\/8002001-8002999#v8002022' data-anchor='#v8002022'>22\u00a0<\/a><\/sup>\u00a0Na\u00b7o\u02b9mi said to her daughter-in-law Ruth: \u201cIt is better, my daughter, for you to go out with his young women than to be harassed in another field.\u201d<\/span>\n<span class=\"parabreak\"><\/span><\/span>\n\n<span class=\"verse\" id=\"v8002023\"><span class=\"style-b first\"><sup class=\"verseNum\"><a href='\/en\/publications\/bible\/nwt\/books\/json\/html\/8002001-8002999#v8002023' data-anchor='#v8002023'>23\u00a0<\/a><\/sup>\u00a0So she stayed close to the young women of Bo\u02b9az and gleaned until the barley harvest<a class=\"xrefLink jsBibleLink\" id=\"xreflink16320947\" href=\"\/en\/publications\/bible\/nwt\/books\/mcr\/16320947\/\" data-bible=\"nwt\" data-targetverses=\"8001022\">+<\/a> and the wheat harvest came to an end. And she kept dwelling with her mother-in-law.<a class=\"xrefLink jsBibleLink\" id=\"xreflink16320956\" href=\"\/en\/publications\/bible\/nwt\/books\/mcr\/16320956\/\" data-bible=\"nwt\" data-targetverses=\"8001016\">+<\/a><\/span><span class=\"parabreak\"><\/span><\/span>\n\n","footnotes":"<div class=\"footnote\" id=\"fn16320354\"><a class=\"fnSourceLink\" href='\/en\/publications\/bible\/nwt\/books\/json\/html\/8002001-8002999#footnotesource16320354' data-anchor='#footnotesource16320354'>^&nbsp;<\/a><span class=\"\">Or possibly, \u201cthe sheaves.\u201d<\/span><\/div>\n\n<div class=\"footnote\" id=\"fn16320397\"><a class=\"fnSourceLink\" href='\/en\/publications\/bible\/nwt\/books\/json\/html\/8002001-8002999#footnotesource16320397' data-anchor='#footnotesource16320397'>^&nbsp;<\/a><span class=\"\">Or \u201cdisturb.\u201d<\/span><\/div>\n\n<div class=\"footnote\" id=\"fn16320538\"><a class=\"fnSourceLink\" href='\/en\/publications\/bible\/nwt\/books\/json\/html\/8002001-8002999#footnotesource16320538' data-anchor='#footnotesource16320538'>^&nbsp;<\/a><span class=\"\">Or \u201ca full reward.\u201d<\/span><\/div>\n\n<div class=\"footnote\" id=\"fn16320563\"><a class=\"fnSourceLink\" href='\/en\/publications\/bible\/nwt\/books\/json\/html\/8002001-8002999#footnotesource16320563' data-anchor='#footnotesource16320563'>^&nbsp;<\/a><span class=\"\">Lit., \u201cspoken to the heart of.\u201d<\/span><\/div>\n\n<div class=\"footnote\" id=\"fn16320645\"><a class=\"fnSourceLink\" href='\/en\/publications\/bible\/nwt\/books\/json\/html\/8002001-8002999#footnotesource16320645' data-anchor='#footnotesource16320645'>^&nbsp;<\/a><span class=\"\">Or possibly, \u201cthe sheaves.\u201d<\/span><\/div>\n\n<div class=\"footnote\" id=\"fn16320703\"><a class=\"fnSourceLink\" href='\/en\/publications\/bible\/nwt\/books\/json\/html\/8002001-8002999#footnotesource16320703' data-anchor='#footnotesource16320703'>^&nbsp;<\/a><span class=\"\">About 22\u00a0L (20\u00a0dry\u00a0qt). See <a class='it pubSym-nwt' data-page-id=\"mid1001061235\" href='\/en\/publications\/bible\/nwt\/appendix-b\/bible-measurements\/'>App.\u00a0B14<\/a>.<\/span><\/div>\n\n<div class=\"footnote\" id=\"fn16320876\"><a class=\"fnSourceLink\" href='\/en\/publications\/bible\/nwt\/books\/json\/html\/8002001-8002999#footnotesource16320876' data-anchor='#footnotesource16320876'>^&nbsp;<\/a><span class=\"\">Or \u201cone of our relatives with the right to repurchase (redeem).\u201d<\/span><\/div>\n\n"}}}