{"status":200,"currentLocale":"en","ranges":{"9028001-9028999":{"citation":"1 Samuel&nbsp;28:1-25","link":"https:\/\/www.jw.org\/en\/publications\/bible\/nwt\/books\/1-samuel\/28\/#v9028001-v9028025","validRange":"9028001-9028025","html":"<span class=\"verse\" id=\"v9028001\"><span class=\"style-b\"><span class=\"chapterNum\"><a href='\/en\/publications\/bible\/nwt\/books\/json\/html\/9028001-9028999#v9028001' data-anchor='#v9028001'>28 <\/a><\/span>\u00a0In those days the Phi\u00b7lis\u02b9tines assembled their armies for war against Israel.<a class=\"xrefLink jsBibleLink\" id=\"xreflink16321723\" href=\"\/en\/publications\/bible\/nwt\/books\/mcr\/16321723\/\" data-bible=\"nwt\" data-targetverses=\"9014052\">+<\/a> So A\u02b9chish said to David: \u201cYou know, of course, that you and your men will go out into battle with me.\u201d<a class=\"xrefLink jsBibleLink\" id=\"xreflink16321736\" href=\"\/en\/publications\/bible\/nwt\/books\/mcr\/16321736\/\" data-bible=\"nwt\" data-targetverses=\"9027012,9029003\">+<\/a><\/span><\/span>\n\n<span class=\"verse\" id=\"v9028002\"><span class=\"style-b\"><sup class=\"verseNum\"><a href='\/en\/publications\/bible\/nwt\/books\/json\/html\/9028001-9028999#v9028002' data-anchor='#v9028002'>2\u00a0<\/a><\/sup>\u00a0At that David said to A\u02b9chish: \u201cYou surely know what your servant will do.\u201d A\u02b9chish said to David: \u201cThat is why I will appoint you as my permanent bodyguard.\u201d<a class=\"footnoteLink\" id=\"footnotesource16321780\" href='\/en\/publications\/bible\/nwt\/books\/json\/html\/9028001-9028999#fn16321780' data-anchor='#fn16321780'>*<\/a><a class=\"xrefLink jsBibleLink\" id=\"xreflink16321764\" href=\"\/en\/publications\/bible\/nwt\/books\/mcr\/16321764\/\" data-bible=\"nwt\" data-targetverses=\"9029002\">+<\/a><\/span>\n<span class=\"parabreak\"><\/span><\/span>\n\n<span class=\"verse\" id=\"v9028003\"><span class=\"style-b first\"><sup class=\"verseNum\"><a href='\/en\/publications\/bible\/nwt\/books\/json\/html\/9028001-9028999#v9028003' data-anchor='#v9028003'>3\u00a0<\/a><\/sup>\u00a0Now Samuel had died, and all Israel had mourned him and had buried him in Ra\u02b9mah, his own city.<a class=\"xrefLink jsBibleLink\" id=\"xreflink16321805\" href=\"\/en\/publications\/bible\/nwt\/books\/mcr\/16321805\/\" data-bible=\"nwt\" data-targetverses=\"9025001\">+<\/a> And Saul had removed the spirit mediums and the fortune-tellers from the land.<a class=\"xrefLink jsBibleLink\" id=\"xreflink16321822\" href=\"\/en\/publications\/bible\/nwt\/books\/mcr\/16321822\/\" data-bible=\"nwt\" data-targetverses=\"2022018,3019031,3020006,3020027,5018010-5018011,66021008\">+<\/a><\/span>\n<span class=\"parabreak\"><\/span><\/span>\n\n<span class=\"verse\" id=\"v9028004\"><span class=\"style-b first\"><sup class=\"verseNum\"><a href='\/en\/publications\/bible\/nwt\/books\/json\/html\/9028001-9028999#v9028004' data-anchor='#v9028004'>4\u00a0<\/a><\/sup>\u00a0The Phi\u00b7lis\u02b9tines assembled and went and set up camp in Shu\u02b9nem.<a class=\"xrefLink jsBibleLink\" id=\"xreflink16321858\" href=\"\/en\/publications\/bible\/nwt\/books\/mcr\/16321858\/\" data-bible=\"nwt\" data-targetverses=\"6019017-6019018,12004008\">+<\/a> So Saul assembled all Israel, and they set up camp in Gil\u00b7bo\u02b9a.<a class=\"xrefLink jsBibleLink\" id=\"xreflink16321870\" href=\"\/en\/publications\/bible\/nwt\/books\/mcr\/16321870\/\" data-bible=\"nwt\" data-targetverses=\"9031001,10001021,10021012\">+<\/a><\/span><\/span>\n\n<span class=\"verse\" id=\"v9028005\"><span class=\"style-b\"><sup class=\"verseNum\"><a href='\/en\/publications\/bible\/nwt\/books\/json\/html\/9028001-9028999#v9028005' data-anchor='#v9028005'>5\u00a0<\/a><\/sup>\u00a0When Saul saw the camp of the Phi\u00b7lis\u02b9tines, he was afraid, and his heart trembled greatly.<a class=\"xrefLink jsBibleLink\" id=\"xreflink16321904\" href=\"\/en\/publications\/bible\/nwt\/books\/mcr\/16321904\/\" data-bible=\"nwt\" data-targetverses=\"9028020\">+<\/a><\/span><\/span>\n\n<span class=\"verse\" id=\"v9028006\"><span class=\"style-b\"><sup class=\"verseNum\"><a href='\/en\/publications\/bible\/nwt\/books\/json\/html\/9028001-9028999#v9028006' data-anchor='#v9028006'>6\u00a0<\/a><\/sup>\u00a0Although Saul would inquire of Jehovah,<a class=\"xrefLink jsBibleLink\" id=\"xreflink16321929\" href=\"\/en\/publications\/bible\/nwt\/books\/mcr\/16321929\/\" data-bible=\"nwt\" data-targetverses=\"9014037\">+<\/a> Jehovah never answered him, either in dreams or by the U\u02b9rim<a class=\"xrefLink jsBibleLink\" id=\"xreflink16321944\" href=\"\/en\/publications\/bible\/nwt\/books\/mcr\/16321944\/\" data-bible=\"nwt\" data-targetverses=\"2028030,4027021\">+<\/a> or through the prophets.<\/span><\/span>\n\n<span class=\"verse\" id=\"v9028007\"><span class=\"style-b\"><sup class=\"verseNum\"><a href='\/en\/publications\/bible\/nwt\/books\/json\/html\/9028001-9028999#v9028007' data-anchor='#v9028007'>7\u00a0<\/a><\/sup>\u00a0Finally Saul said to his servants: \u201cFind me a woman who is a spirit medium,<a class=\"xrefLink jsBibleLink\" id=\"xreflink16321968\" href=\"\/en\/publications\/bible\/nwt\/books\/mcr\/16321968\/\" data-bible=\"nwt\" data-targetverses=\"2022018,3019031,3020006,9015023,9028003\">+<\/a> and I will go and consult her.\u201d His servants replied: \u201cLook! There is a woman who is a spirit medium in En-dor.\u201d<a class=\"xrefLink jsBibleLink\" id=\"xreflink16321994\" href=\"\/en\/publications\/bible\/nwt\/books\/mcr\/16321994\/\" data-bible=\"nwt\" data-targetverses=\"6017011\">+<\/a><\/span>\n<span class=\"parabreak\"><\/span><\/span>\n\n<span class=\"verse\" id=\"v9028008\"><span class=\"style-b first\"><sup class=\"verseNum\"><a href='\/en\/publications\/bible\/nwt\/books\/json\/html\/9028001-9028999#v9028008' data-anchor='#v9028008'>8\u00a0<\/a><\/sup>\u00a0So Saul disguised himself and put on other garments and went to the woman by night with two of his men. He said: \u201cUse divination, please, by acting as a spirit medium,<a class=\"xrefLink jsBibleLink\" id=\"xreflink16322019\" href=\"\/en\/publications\/bible\/nwt\/books\/mcr\/16322019\/\" data-bible=\"nwt\" data-targetverses=\"5018010-5018011,13010013\">+<\/a> and bring up for me the one whom I designate to you.\u201d<\/span><\/span>\n\n<span class=\"verse\" id=\"v9028009\"><span class=\"style-b\"><sup class=\"verseNum\"><a href='\/en\/publications\/bible\/nwt\/books\/json\/html\/9028001-9028999#v9028009' data-anchor='#v9028009'>9\u00a0<\/a><\/sup>\u00a0However, the woman said to him: \u201cYou must know what Saul did, how he removed the spirit mediums and the fortune-tellers from the land.<a class=\"xrefLink jsBibleLink\" id=\"xreflink16322060\" href=\"\/en\/publications\/bible\/nwt\/books\/mcr\/16322060\/\" data-bible=\"nwt\" data-targetverses=\"9028003\">+<\/a> Why, then, are you trying to trap me<a class=\"footnoteLink\" id=\"footnotesource16322104\" href='\/en\/publications\/bible\/nwt\/books\/json\/html\/9028001-9028999#fn16322104' data-anchor='#fn16322104'>*<\/a> to have me put to death?\u201d<a class=\"xrefLink jsBibleLink\" id=\"xreflink16322084\" href=\"\/en\/publications\/bible\/nwt\/books\/mcr\/16322084\/\" data-bible=\"nwt\" data-targetverses=\"2022018,3020027\">+<\/a><\/span><\/span>\n\n<span class=\"verse\" id=\"v9028010\"><span class=\"style-b\"><sup class=\"verseNum\"><a href='\/en\/publications\/bible\/nwt\/books\/json\/html\/9028001-9028999#v9028010' data-anchor='#v9028010'>10\u00a0<\/a><\/sup>\u00a0Saul then swore to her by Jehovah, saying: \u201cAs surely as Jehovah is alive, you will not incur any guilt in this matter!\u201d<\/span><\/span>\n\n<span class=\"verse\" id=\"v9028011\"><span class=\"style-b\"><sup class=\"verseNum\"><a href='\/en\/publications\/bible\/nwt\/books\/json\/html\/9028001-9028999#v9028011' data-anchor='#v9028011'>11\u00a0<\/a><\/sup>\u00a0At this the woman said: \u201cWhom should I bring up for you?\u201d He replied: \u201cBring up Samuel for me.\u201d<\/span><\/span>\n\n<span class=\"verse\" id=\"v9028012\"><span class=\"style-b\"><sup class=\"verseNum\"><a href='\/en\/publications\/bible\/nwt\/books\/json\/html\/9028001-9028999#v9028012' data-anchor='#v9028012'>12\u00a0<\/a><\/sup>\u00a0When the woman saw \u201cSamuel,\u201d<a class=\"footnoteLink\" id=\"footnotesource16322187\" href='\/en\/publications\/bible\/nwt\/books\/json\/html\/9028001-9028999#fn16322187' data-anchor='#fn16322187'>*<\/a><a class=\"xrefLink jsBibleLink\" id=\"xreflink16322167\" href=\"\/en\/publications\/bible\/nwt\/books\/mcr\/16322167\/\" data-bible=\"nwt\" data-targetverses=\"9028003\">+<\/a> she cried out at the top of her voice and said to Saul: \u201cWhy did you trick me? You are Saul!\u201d<\/span><\/span>\n\n<span class=\"verse\" id=\"v9028013\"><span class=\"style-b\"><sup class=\"verseNum\"><a href='\/en\/publications\/bible\/nwt\/books\/json\/html\/9028001-9028999#v9028013' data-anchor='#v9028013'>13\u00a0<\/a><\/sup>\u00a0The king said to her: \u201cDo not be afraid, but what do you see?\u201d The woman replied to Saul: \u201cI see one like a god coming up out of the earth.\u201d<\/span><\/span>\n\n<span class=\"verse\" id=\"v9028014\"><span class=\"style-b\"><sup class=\"verseNum\"><a href='\/en\/publications\/bible\/nwt\/books\/json\/html\/9028001-9028999#v9028014' data-anchor='#v9028014'>14\u00a0<\/a><\/sup>\u00a0At once he asked her: \u201cWhat does he look like?\u201d to which she said: \u201cIt is an old man coming up, and he is clothed in a sleeveless coat.\u201d<a class=\"xrefLink jsBibleLink\" id=\"xreflink16322227\" href=\"\/en\/publications\/bible\/nwt\/books\/mcr\/16322227\/\" data-bible=\"nwt\" data-targetverses=\"9015027\">+<\/a> At that Saul realized that it was \u201cSamuel,\u201d and he bowed low with his face to the ground and prostrated himself.<\/span>\n<span class=\"parabreak\"><\/span><\/span>\n\n<span class=\"verse\" id=\"v9028015\"><span class=\"style-b first\"><sup class=\"verseNum\"><a href='\/en\/publications\/bible\/nwt\/books\/json\/html\/9028001-9028999#v9028015' data-anchor='#v9028015'>15\u00a0<\/a><\/sup>\u00a0Then \u201cSamuel\u201d said to Saul: \u201cWhy have you disturbed me by having me brought up?\u201d Saul replied: \u201cI am in great trouble. The Phi\u00b7lis\u02b9tines are fighting against me, and God has departed from me and no longer answers me, either through the prophets or in dreams;<a class=\"xrefLink jsBibleLink\" id=\"xreflink16322249\" href=\"\/en\/publications\/bible\/nwt\/books\/mcr\/16322249\/\" data-bible=\"nwt\" data-targetverses=\"9028006\">+<\/a> so that is why I am calling on you to let me know what I should do.\u201d<a class=\"xrefLink jsBibleLink\" id=\"xreflink16322264\" href=\"\/en\/publications\/bible\/nwt\/books\/mcr\/16322264\/\" data-bible=\"nwt\" data-targetverses=\"3019031\">+<\/a><\/span>\n<span class=\"parabreak\"><\/span><\/span>\n\n<span class=\"verse\" id=\"v9028016\"><span class=\"style-b first\"><sup class=\"verseNum\"><a href='\/en\/publications\/bible\/nwt\/books\/json\/html\/9028001-9028999#v9028016' data-anchor='#v9028016'>16\u00a0<\/a><\/sup>\u00a0And \u201cSamuel\u201d said: \u201cWhy do you inquire of me now that Jehovah has departed from you<a class=\"xrefLink jsBibleLink\" id=\"xreflink16322281\" href=\"\/en\/publications\/bible\/nwt\/books\/mcr\/16322281\/\" data-bible=\"nwt\" data-targetverses=\"9015023,9016014\">+<\/a> and has become your adversary?<\/span><\/span>\n\n<span class=\"verse\" id=\"v9028017\"><span class=\"style-b\"><sup class=\"verseNum\"><a href='\/en\/publications\/bible\/nwt\/books\/json\/html\/9028001-9028999#v9028017' data-anchor='#v9028017'>17\u00a0<\/a><\/sup>\u00a0Jehovah will do for himself what he foretold through me: Jehovah will rip the kingdom out of your hands and give it to one of your fellow men, David.<a class=\"xrefLink jsBibleLink\" id=\"xreflink16322317\" href=\"\/en\/publications\/bible\/nwt\/books\/mcr\/16322317\/\" data-bible=\"nwt\" data-targetverses=\"9013014,9015028,9016013,9024020\">+<\/a><\/span><\/span>\n\n<span class=\"verse\" id=\"v9028018\"><span class=\"style-b\"><sup class=\"verseNum\"><a href='\/en\/publications\/bible\/nwt\/books\/json\/html\/9028001-9028999#v9028018' data-anchor='#v9028018'>18\u00a0<\/a><\/sup>\u00a0Because you did not obey the voice of Jehovah and you did not execute his burning anger against the A\u00b7mal\u02b9ek\u00b7ites,<a class=\"xrefLink jsBibleLink\" id=\"xreflink16322351\" href=\"\/en\/publications\/bible\/nwt\/books\/mcr\/16322351\/\" data-bible=\"nwt\" data-targetverses=\"9015009,13010013\">+<\/a> that is why Jehovah is doing this to you this day.<\/span><\/span>\n\n<span class=\"verse\" id=\"v9028019\"><span class=\"style-b\"><sup class=\"verseNum\"><a href='\/en\/publications\/bible\/nwt\/books\/json\/html\/9028001-9028999#v9028019' data-anchor='#v9028019'>19\u00a0<\/a><\/sup>\u00a0Jehovah will also give both Israel and you into the hand of the Phi\u00b7lis\u02b9tines,<a class=\"xrefLink jsBibleLink\" id=\"xreflink16322384\" href=\"\/en\/publications\/bible\/nwt\/books\/mcr\/16322384\/\" data-bible=\"nwt\" data-targetverses=\"9028001,9031001\">+<\/a> and tomorrow you<a class=\"xrefLink jsBibleLink\" id=\"xreflink16322407\" href=\"\/en\/publications\/bible\/nwt\/books\/mcr\/16322407\/\" data-bible=\"nwt\" data-targetverses=\"9031005\">+<\/a> and your sons<a class=\"xrefLink jsBibleLink\" id=\"xreflink16322427\" href=\"\/en\/publications\/bible\/nwt\/books\/mcr\/16322427\/\" data-bible=\"nwt\" data-targetverses=\"9031002,10002008\">+<\/a> will be with me. Jehovah will also give the army of Israel into the hands of the Phi\u00b7lis\u02b9tines.\u201d<a class=\"xrefLink jsBibleLink\" id=\"xreflink16322444\" href=\"\/en\/publications\/bible\/nwt\/books\/mcr\/16322444\/\" data-bible=\"nwt\" data-targetverses=\"9031007\">+<\/a><\/span>\n<span class=\"parabreak\"><\/span><\/span>\n\n<span class=\"verse\" id=\"v9028020\"><span class=\"style-b first\"><sup class=\"verseNum\"><a href='\/en\/publications\/bible\/nwt\/books\/json\/html\/9028001-9028999#v9028020' data-anchor='#v9028020'>20\u00a0<\/a><\/sup>\u00a0At once Saul fell full length on the ground and became very much afraid because of \u201cSamuel\u2019s\u201d words. And there was no strength left in him, because he had not eaten food all day and all night.<\/span><\/span>\n\n<span class=\"verse\" id=\"v9028021\"><span class=\"style-b\"><sup class=\"verseNum\"><a href='\/en\/publications\/bible\/nwt\/books\/json\/html\/9028001-9028999#v9028021' data-anchor='#v9028021'>21\u00a0<\/a><\/sup>\u00a0When the woman came to Saul and saw that he had been greatly disturbed, she said to him: \u201cHere your servant has obeyed what you said, and I risked my life<a class=\"footnoteLink\" id=\"footnotesource16322499\" href='\/en\/publications\/bible\/nwt\/books\/json\/html\/9028001-9028999#fn16322499' data-anchor='#fn16322499'>*<\/a><a class=\"xrefLink jsBibleLink\" id=\"xreflink16322485\" href=\"\/en\/publications\/bible\/nwt\/books\/mcr\/16322485\/\" data-bible=\"nwt\" data-targetverses=\"3020027\">+<\/a> and did what you told me to do.<\/span><\/span>\n\n<span class=\"verse\" id=\"v9028022\"><span class=\"style-b\"><sup class=\"verseNum\"><a href='\/en\/publications\/bible\/nwt\/books\/json\/html\/9028001-9028999#v9028022' data-anchor='#v9028022'>22\u00a0<\/a><\/sup>\u00a0Now, please, listen to what your servant has to say. Let me set before you a piece of bread; then eat so that you will have some strength to go on your way.\u201d<\/span><\/span>\n\n<span class=\"verse\" id=\"v9028023\"><span class=\"style-b\"><sup class=\"verseNum\"><a href='\/en\/publications\/bible\/nwt\/books\/json\/html\/9028001-9028999#v9028023' data-anchor='#v9028023'>23\u00a0<\/a><\/sup>\u00a0But he refused and said: \u201cI am not going to eat.\u201d However, his servants and also the woman kept urging him. Finally he listened to them and got up from the ground and sat on the bed.<\/span><\/span>\n\n<span class=\"verse\" id=\"v9028024\"><span class=\"style-b\"><sup class=\"verseNum\"><a href='\/en\/publications\/bible\/nwt\/books\/json\/html\/9028001-9028999#v9028024' data-anchor='#v9028024'>24\u00a0<\/a><\/sup>\u00a0The woman had a fattened calf in the house, so she quickly slaughtered<a class=\"footnoteLink\" id=\"footnotesource16322576\" href='\/en\/publications\/bible\/nwt\/books\/json\/html\/9028001-9028999#fn16322576' data-anchor='#fn16322576'>*<\/a> it and took flour and kneaded dough and baked it into unleavened bread.<\/span><\/span>\n\n<span class=\"verse\" id=\"v9028025\"><span class=\"style-b\"><sup class=\"verseNum\"><a href='\/en\/publications\/bible\/nwt\/books\/json\/html\/9028001-9028999#v9028025' data-anchor='#v9028025'>25\u00a0<\/a><\/sup>\u00a0She served them to Saul and his servants, and they ate. After that they rose up and left during the night.<a class=\"xrefLink jsBibleLink\" id=\"xreflink16322609\" href=\"\/en\/publications\/bible\/nwt\/books\/mcr\/16322609\/\" data-bible=\"nwt\" data-targetverses=\"9028008\">+<\/a><\/span><span class=\"parabreak\"><\/span><\/span>\n\n","footnotes":"<div class=\"footnote\" id=\"fn16321780\"><a class=\"fnSourceLink\" href='\/en\/publications\/bible\/nwt\/books\/json\/html\/9028001-9028999#footnotesource16321780' data-anchor='#footnotesource16321780'>^&nbsp;<\/a><span class=\"\">Lit., \u201cas guardian of my head all the days.\u201d<\/span><\/div>\n\n<div class=\"footnote\" id=\"fn16322104\"><a class=\"fnSourceLink\" href='\/en\/publications\/bible\/nwt\/books\/json\/html\/9028001-9028999#footnotesource16322104' data-anchor='#footnotesource16322104'>^&nbsp;<\/a><span class=\"\">Or \u201cmy soul.\u201d<\/span><\/div>\n\n<div class=\"footnote\" id=\"fn16322187\"><a class=\"fnSourceLink\" href='\/en\/publications\/bible\/nwt\/books\/json\/html\/9028001-9028999#footnotesource16322187' data-anchor='#footnotesource16322187'>^&nbsp;<\/a><span class=\"\">Or \u201cwhat appeared to be Samuel.\u201d<\/span><\/div>\n\n<div class=\"footnote\" id=\"fn16322499\"><a class=\"fnSourceLink\" href='\/en\/publications\/bible\/nwt\/books\/json\/html\/9028001-9028999#footnotesource16322499' data-anchor='#footnotesource16322499'>^&nbsp;<\/a><span class=\"\">Or \u201ctook my soul in my hand.\u201d<\/span><\/div>\n\n<div class=\"footnote\" id=\"fn16322576\"><a class=\"fnSourceLink\" href='\/en\/publications\/bible\/nwt\/books\/json\/html\/9028001-9028999#footnotesource16322576' data-anchor='#footnotesource16322576'>^&nbsp;<\/a><span class=\"\">Or \u201csacrificed.\u201d<\/span><\/div>\n\n"}}}